[
  {
    "audio": [],
    "categories": [
      "motoring_problems_and_accidents"
    ],
    "level": [
      "C2"
    ],
    "materials": [
      {
        "meanings": [
          {
            "antonyms": [],
            "definitions": [
              {
                "definition": "to crash violently into something, especially because you are driving too fast or not paying enough attention",
                "example": "A truck plowed into the back of the bus."
              }
            ],
            "part_of_speech": "phrasal verb",
            "synonyms": []
          },
          {
            "antonyms": [],
            "definitions": [
              {
                "definition": "to invest a large amount of money in a company or project",
                "example": "The government has plowed more than $20 billion into building new schools."
              }
            ],
            "part_of_speech": "phrasal verb",
            "synonyms": []
          }
        ],
        "phonetics": []
      }
    ],
    "photo": "plow into_05122024.jpg",
    "word": "plow into"
  },
  {
    "audio": [
      "dockless bike_478_06_12_2024.mp3",
      "dockless bike_323_06_12_2024.mp3"
    ],
    "categories": [
      "cycling",
      "types_of_vehicle"
    ],
    "level": [
      "C2"
    ],
    "materials": [
      {
        "meanings": [
          {
            "antonyms": [],
            "definitions": [
              {
                "definition": "a bicycle that can be rented for a short period of time and left in any public space once the user has finished with it.  Dockless bikes  are usually paid for and located by using an app on the user's mobile phone.",
                "example": "There are several different companies operating dockless bikes in the city."
              }
            ],
            "part_of_speech": "noun",
            "synonyms": []
          }
        ],
        "phonetics": [
          "/ˌdɒkləs ˈbaɪk/",
          "/ˌdɑːkləs ˈbaɪk/"
        ]
      }
    ],
    "photo": "dockless bike_05122024.jpg",
    "word": "dockless bike"
  },
  {
    "audio": [
      "occupational therapist_280_06_12_2024.mp3",
      "occupational therapist_052_06_12_2024.mp3"
    ],
    "categories": [
      "medical_staff"
    ],
    "level": [
      "C2"
    ],
    "materials": [
      {
        "meanings": [
          {
            "antonyms": [],
            "definitions": [
              {
                "definition": "a person whose job is to help people get better after illness or injury by giving them special activities to do",
                "example": null
              }
            ],
            "part_of_speech": "noun",
            "synonyms": []
          }
        ],
        "phonetics": [
          "/ˌɑːkjuˌpeɪʃənl ˈθerəpɪst/",
          "/ˌɒkjuˌpeɪʃənl ˈθerəpɪst/"
        ]
      }
    ],
    "photo": "occupational therapist_05122024.jpg",
    "word": "occupational therapist"
  },
  {
    "audio": [
      "side dish_674_06_12_2024.mp3",
      "side dish_860_06_12_2024.mp3"
    ],
    "categories": [
      "meals"
    ],
    "level": [
      "C1"
    ],
    "materials": [
      {
        "meanings": [
          {
            "antonyms": [],
            "definitions": [
              {
                "definition": "a small amount of food, for example a salad, served with the main course of a meal",
                "example": "a side dish of fresh vegetables"
              }
            ],
            "part_of_speech": "noun",
            "synonyms": []
          }
        ],
        "phonetics": [
          "/ˈsaɪd dɪʃ/"
        ]
      }
    ],
    "photo": "side dish_05122024.jpg",
    "word": "side dish"
  },
  {
    "audio": [
      "boom town_231_06_12_2024.mp3",
      "boom town_446_06_12_2024.mp3"
    ],
    "categories": [
      "successful_things"
    ],
    "level": [
      "C2"
    ],
    "materials": [
      {
        "meanings": [
          {
            "antonyms": [],
            "definitions": [
              {
                "definition": "a town that has become rich and successful because trade and industry has developed there",
                "example": null
              }
            ],
            "part_of_speech": "noun",
            "synonyms": []
          }
        ],
        "phonetics": [
          "/ˈbuːm taʊn/"
        ]
      }
    ],
    "photo": "boom town_05122024.jpg",
    "word": "boom town"
  },
  {
    "audio": [
      "light heavyweight_996_06_12_2024.mp3",
      "light heavyweight_203_06_12_2024.mp3"
    ],
    "categories": [
      "combat_sports"
    ],
    "level": [
      "C2"
    ],
    "materials": [
      {
        "meanings": [
          {
            "antonyms": [],
            "definitions": [
              {
                "definition": "a weight in  boxing  and other sports, between  middleweight  and  heavyweight , in  boxing  usually between 75 and 81  kilograms ; a  boxer  or other competitor in this class",
                "example": "a light heavyweight champion"
              }
            ],
            "part_of_speech": "noun",
            "synonyms": []
          }
        ],
        "phonetics": [
          "/ˌlaɪt ˈheviweɪt/"
        ]
      }
    ],
    "photo": "light heavyweight_05122024.jpg",
    "word": "light heavyweight"
  },
  {
    "audio": [
      "global economy_699_06_12_2024.mp3",
      "global economy_529_06_12_2024.mp3"
    ],
    "categories": [
      "the_economy"
    ],
    "level": [
      "B2"
    ],
    "materials": [
      {
        "meanings": [
          {
            "antonyms": [],
            "definitions": [
              {
                "definition": "the economies of every country in the world considered as a single economic system",
                "example": "The Covid-19 pandemic knocked the global economy into recession."
              }
            ],
            "part_of_speech": "noun",
            "synonyms": []
          }
        ],
        "phonetics": [
          "/ˌɡləʊbl ɪˈkɑːnəmi/",
          "/ˌɡləʊbl ɪˈkɒnəmi/"
        ]
      }
    ],
    "photo": "global economy_05122024.jpg",
    "word": "global economy"
  },
  {
    "audio": [
      "destination charge_288_06_12_2024.mp3",
      "destination charge_057_06_12_2024.mp3"
    ],
    "categories": [
      "the_car_industry"
    ],
    "level": [
      "C2"
    ],
    "materials": [
      {
        "meanings": [
          {
            "antonyms": [],
            "definitions": [
              {
                "definition": "a fee added to the price of a new car to cover the cost of transporting the vehicle from the factory where it was made to the place where it is to be sold",
                "example": "The price that you pay for a new car in a dealership includes all kind of extra fees such as a destination charge and sales tax."
              }
            ],
            "part_of_speech": "noun",
            "synonyms": []
          }
        ],
        "phonetics": [
          "/ˌdestɪˈneɪʃn tʃɑːrdʒ/",
          "/ˌdestɪˈneɪʃn tʃɑːdʒ/"
        ]
      }
    ],
    "photo": "destination charge_05122024.jpg",
    "word": "destination charge"
  },
  {
    "audio": [
      "German measles_686_06_12_2024.mp3",
      "German measles_908_06_12_2024.mp3"
    ],
    "categories": [
      "types_of_illness"
    ],
    "level": [
      "C2"
    ],
    "materials": [
      {
        "meanings": [
          {
            "antonyms": [],
            "definitions": [
              {
                "definition": "a mild disease that causes a  sore  throat  (= a painful throat because of an infection)  and red spots all over the body. It can seriously affect babies born to women who catch it soon after they become pregnant.",
                "example": null
              }
            ],
            "part_of_speech": "noun",
            "synonyms": []
          }
        ],
        "phonetics": [
          "/ˌdʒɜːrmən ˈmiːzlz/",
          "/ˌdʒɜːmən ˈmiːzlz/"
        ]
      }
    ],
    "photo": "German measles_05122024.jpg",
    "word": "German measles"
  },
  {
    "audio": [
      "environmental art_259_06_12_2024.mp3",
      "environmental art_457_06_12_2024.mp3"
    ],
    "categories": [
      "artwork_and_techniques"
    ],
    "level": [
      "C2"
    ],
    "materials": [
      {
        "meanings": [
          {
            "antonyms": [],
            "definitions": [
              {
                "definition": "art that is meant to enhance the environment or draw attention to environmental issues",
                "example": null
              }
            ],
            "part_of_speech": "noun",
            "synonyms": []
          }
        ],
        "phonetics": [
          "/ɪnˌvaɪrənmentl ˈɑːrt/",
          "/ɪnˌvaɪrənmentl ˈɑːt/"
        ]
      }
    ],
    "photo": "environmental art_05122024.jpg",
    "word": "environmental art"
  },
  {
    "audio": [
      "Eastern Daylight Time_971_06_12_2024.mp3",
      "Eastern Daylight Time_771_06_12_2024.mp3"
    ],
    "categories": [
      "time_zones"
    ],
    "level": [
      "C2"
    ],
    "materials": [
      {
        "meanings": [
          {
            "antonyms": [],
            "definitions": [
              {
                "definition": "the time used in the summer in the eastern US and Canada, which is four hours earlier than UTC",
                "example": null
              }
            ],
            "part_of_speech": "noun",
            "synonyms": []
          }
        ],
        "phonetics": [
          "/ˌiːstən ˈdeɪlaɪt taɪm/",
          "/ˌiːstərn ˈdeɪlaɪt taɪm/"
        ]
      }
    ],
    "photo": "Eastern Daylight Time_05122024.jpg",
    "word": "Eastern Daylight Time"
  },
  {
    "audio": [
      "sales clerk_907_06_12_2024.mp3",
      "sales clerk_226_06_12_2024.mp3"
    ],
    "categories": [
      "jobs_and_professions",
      "shopping_in_stores"
    ],
    "level": [
      "C1"
    ],
    "materials": [
      {
        "meanings": [
          {
            "antonyms": [],
            "definitions": [
              {
                "definition": "a person whose job is to serve customers in a shop",
                "example": null
              }
            ],
            "part_of_speech": "noun",
            "synonyms": []
          }
        ],
        "phonetics": [
          "/ˈseɪlz klɑːk/",
          "/ˈseɪlz klɜːrk/"
        ]
      }
    ],
    "photo": "sales clerk_05122024.jpg",
    "word": "sales clerk"
  },
  {
    "audio": [
      "digital economy_060_06_12_2024.mp3",
      "digital economy_680_06_12_2024.mp3"
    ],
    "categories": [
      "the_economy"
    ],
    "level": [
      "B2"
    ],
    "materials": [
      {
        "meanings": [
          {
            "antonyms": [],
            "definitions": [
              {
                "definition": "an economy that functions mostly through the use of digital technology, especially the internet",
                "example": "India's digital economy is forecast to grow at a rate of 20% per year."
              }
            ],
            "part_of_speech": "noun",
            "synonyms": []
          }
        ],
        "phonetics": [
          "/ˌdɪdʒɪtl ɪˈkɒnəmi/",
          "/ˌdɪdʒɪtl ɪˈkɑːnəmi/"
        ]
      }
    ],
    "photo": "digital economy_05122024.jpg",
    "word": "digital economy"
  },
  {
    "audio": [
      "whisky mac_371_06_12_2024.mp3",
      "whisky mac_204_06_12_2024.mp3"
    ],
    "categories": [
      "alcoholic_drinks"
    ],
    "level": [
      "C2"
    ],
    "materials": [
      {
        "meanings": [
          {
            "antonyms": [],
            "definitions": [
              {
                "definition": "an alcoholic drink made by mixing  whisky  with  ginger wine",
                "example": null
              }
            ],
            "part_of_speech": "noun",
            "synonyms": []
          }
        ],
        "phonetics": [
          "/ˌwɪski ˈmæk/"
        ]
      }
    ],
    "photo": "whisky mac_05122024.jpg",
    "word": "whisky mac"
  },
  {
    "audio": [
      "climate emergency_264_06_12_2024.mp3",
      "climate emergency_925_06_12_2024.mp3"
    ],
    "categories": [
      "climate_change"
    ],
    "level": [
      "B1"
    ],
    "materials": [
      {
        "meanings": [
          {
            "antonyms": [],
            "definitions": [
              {
                "definition": "a situation in which immediate action is needed to reduce or stop  climate change  and prevent serious and permanent damage to the environment",
                "example": "Halifax became the second Canadian city to  declare a climate emergency ."
              }
            ],
            "part_of_speech": "noun",
            "synonyms": []
          }
        ],
        "phonetics": [
          "/ˈklaɪmət ɪmɜːrdʒənsi/",
          "/ˈklaɪmət ɪmɜːdʒənsi/"
        ]
      }
    ],
    "photo": "climate emergency_05122024.jpg",
    "word": "climate emergency"
  }
]