[
  {
    "audio": [
      "Bodhisattva_191_05_12_2024.mp3"
    ],
    "categories": [
      "religious_people"
    ],
    "level": [
      "C2"
    ],
    "materials": [
      {
        "meanings": [
          {
            "antonyms": [],
            "definitions": [
              {
                "definition": "A person who has taken specific lay or monastic vows and who is on the road to perfect knowledge; specifically, one who foregoes personal nirvana in order to help others achieve enlightenment.",
                "example": null
              },
              {
                "definition": "An enlightened being existing in a form of existence beyond the ordinary forms of physical reality understood and acknowledged by scientific thought, resembling the Western notion of angels, but with a wealth of its own nuances and expectations. These include the compassionate working for enlightenment of all sentient beings.",
                "example": null
              }
            ],
            "part_of_speech": "noun",
            "synonyms": [
              "mahasattva"
            ]
          }
        ],
        "phonetics": [
          "/boʊ̯diːˈsɑtvə/"
        ]
      }
    ],
    "photo": "Bodhisattva_05122024.jpg",
    "word": "Bodhisattva"
  },
  {
    "audio": null,
    "categories": [
      "international_relations"
    ],
    "level": [
      "C2"
    ],
    "materials": [
      {
        "meanings": [
          {
            "antonyms": [],
            "definitions": [
              {
                "definition": "Taking place across a border.",
                "example": null
              }
            ],
            "part_of_speech": "adjective",
            "synonyms": []
          },
          {
            "antonyms": [],
            "definitions": [
              {
                "definition": "Across a border.",
                "example": null
              }
            ],
            "part_of_speech": "adverb",
            "synonyms": []
          }
        ],
        "phonetics": []
      }
    ],
    "photo": "cross-border_05122024.jpg",
    "word": "cross-border"
  },
  {
    "audio": [
      "trek_264_05_12_2024.mp3"
    ],
    "categories": [
      "types_of_holiday_vacation"
    ],
    "level": [
      "B2"
    ],
    "materials": [
      {
        "meanings": [
          {
            "antonyms": [],
            "definitions": [
              {
                "definition": "A journey by ox wagon.",
                "example": null
              },
              {
                "definition": "The Boer migration of 1835-1837.",
                "example": null
              },
              {
                "definition": "A slow or difficult journey.",
                "example": "We're planning a trek up Kilimanjaro."
              },
              {
                "definition": "A long walk.",
                "example": "I would drive to the shops from here; you can walk, but it's quite a trek."
              }
            ],
            "part_of_speech": "noun",
            "synonyms": [
              "slog"
            ]
          },
          {
            "antonyms": [],
            "definitions": [
              {
                "definition": "To make a slow or arduous journey.",
                "example": null
              },
              {
                "definition": "To journey on foot, especially to hike through mountainous areas.",
                "example": null
              },
              {
                "definition": "To travel by ox wagon.",
                "example": null
              }
            ],
            "part_of_speech": "verb",
            "synonyms": []
          }
        ],
        "phonetics": [
          "/tɹɛk/"
        ]
      }
    ],
    "photo": "trek_05122024.jpg",
    "word": "trek"
  },
  {
    "audio": null,
    "categories": [
      "annoying"
    ],
    "level": [
      "C2"
    ],
    "materials": [
      {
        "meanings": [
          {
            "antonyms": [],
            "definitions": [
              {
                "definition": "Not sufferable; very difficult or impossible to endure.",
                "example": null
              }
            ],
            "part_of_speech": "adjective",
            "synonyms": [
              "intolerable",
              "unbearable"
            ]
          }
        ],
        "phonetics": [
          "/ɪnˈsʌfɚəbəl/",
          "[ɪnˈsʌfɹəbl̩]"
        ]
      }
    ],
    "photo": "insufferable_05122024.jpg",
    "word": "insufferable"
  },
  {
    "audio": null,
    "categories": [
      "describing_geographic_regions"
    ],
    "level": [
      "B1"
    ],
    "materials": [
      {
        "meanings": [
          {
            "antonyms": [],
            "definitions": [
              {
                "definition": "Of, facing, situated in, or related to the north-east",
                "example": null
              },
              {
                "definition": "(of a wind) blowing from the north-east; north-easterly",
                "example": null
              }
            ],
            "part_of_speech": "adjective",
            "synonyms": []
          }
        ],
        "phonetics": []
      }
    ],
    "photo": "north-eastern_05122024.jpg",
    "word": "north-eastern"
  },
  {
    "audio": null,
    "categories": [
      "the_air_force"
    ],
    "level": [
      "C2"
    ],
    "materials": [
      {
        "meanings": [
          {
            "antonyms": [],
            "definitions": [
              {
                "definition": "A rank in the RAF, between that of flying officer and squadron leader, of a person in charge of a flight of aircraft, equivalent to a Royal Navy lieutenant or an Army captain",
                "example": null
              }
            ],
            "part_of_speech": "noun",
            "synonyms": [
              "F/L"
            ]
          }
        ],
        "phonetics": []
      }
    ],
    "photo": "flight_lieutenant_05122024.jpg",
    "word": "flight lieutenant"
  },
  {
    "audio": null,
    "categories": [
      "selfish"
    ],
    "level": [
      "C2"
    ],
    "materials": [
      {
        "meanings": [
          {
            "antonyms": [],
            "definitions": [
              {
                "definition": "Overly concerned about oneself, to the point of ignoring the feelings of others.",
                "example": "I don't want to call him self-absorbed but he was more concerned with the scratch on his car than the people in the car he hit."
              }
            ],
            "part_of_speech": "adjective",
            "synonyms": [
              "inconsiderate"
            ]
          }
        ],
        "phonetics": []
      }
    ],
    "photo": "self-absorbed_05122024.jpg",
    "word": "self-absorbed"
  },
  {
    "audio": null,
    "categories": [
      "board_games"
    ],
    "level": [
      "C2"
    ],
    "materials": [
      {
        "meanings": [
          {
            "antonyms": [],
            "definitions": [
              {
                "definition": "A children's luck-based board game of Indian origin, played on a numbered grid, the aim of which is to proceed to the end, and in which ladders aid progress and snakes impede it.",
                "example": null
              },
              {
                "definition": "Any situation in which people or events go forward and backward, seemingly at random",
                "example": null
              }
            ],
            "part_of_speech": "noun",
            "synonyms": [
              "chutes and ladders"
            ]
          }
        ],
        "phonetics": []
      }
    ],
    "photo": "snakes_and_ladders_05122024.jpg",
    "word": "snakes and ladders"
  },
  {
    "audio": [
      "under the influence_903_05_12_2024.mp3"
    ],
    "categories": [
      "drugs"
    ],
    "level": [
      "C2"
    ],
    "materials": [
      {
        "meanings": [
          {
            "antonyms": [],
            "definitions": [
              {
                "definition": "Intoxicated, inebriated, or otherwise stupefied by an ingested mind-altering substance, typically alcohol; drunk.",
                "example": "He was arrested for driving under the influence."
              }
            ],
            "part_of_speech": "adverb",
            "synonyms": []
          }
        ],
        "phonetics": []
      }
    ],
    "photo": "under_the_influence_05122024.jpg",
    "word": "under the influence"
  },
  {
    "audio": [
      "googly_717_05_12_2024.mp3"
    ],
    "categories": [
      "cricket"
    ],
    "level": [
      "C2"
    ],
    "materials": [
      {
        "meanings": [
          {
            "antonyms": [],
            "definitions": [
              {
                "definition": "A ball, bowled by a leg-break bowler, that spins from off to leg (to a right-handed batsman), unlike a normal leg-break delivery.",
                "example": null
              }
            ],
            "part_of_speech": "noun",
            "synonyms": [
              "bosey",
              "bosie",
              "wrong ’un"
            ]
          }
        ],
        "phonetics": [
          "/ˈɡʉːɡli/",
          "/ˈɡuɡli/"
        ]
      },
      {
        "meanings": [
          {
            "antonyms": [],
            "definitions": [
              {
                "definition": "(of the eyes) Bulging.",
                "example": null
              },
              {
                "definition": "(usually of eyes, sometimes of persons) Appearing to be amorous, flirtatious.",
                "example": null
              }
            ],
            "part_of_speech": "adjective",
            "synonyms": []
          }
        ],
        "phonetics": [
          "/ˈɡʉːɡli/",
          "/ˈɡuɡli/"
        ]
      }
    ],
    "photo": "googly_05122024.jpg",
    "word": "googly"
  },
  {
    "audio": [
      "fowl_275_05_12_2024.mp3"
    ],
    "categories": [
      "birds",
      "meat_fish_and_seafood"
    ],
    "level": [
      "C2"
    ],
    "materials": [
      {
        "meanings": [
          {
            "antonyms": [],
            "definitions": [
              {
                "definition": "A bird.",
                "example": null
              },
              {
                "definition": "A bird of the order Galliformes, including chickens, turkeys, pheasant, partridges and quail.",
                "example": null
              },
              {
                "definition": "Birds which are hunted or kept for food, including Galliformes and also waterfowl of the order Anseriformes such as ducks, geese and swans.",
                "example": null
              }
            ],
            "part_of_speech": "noun",
            "synonyms": []
          },
          {
            "antonyms": [],
            "definitions": [
              {
                "definition": "To hunt fowl.",
                "example": "We took our guns and went fowling."
              }
            ],
            "part_of_speech": "verb",
            "synonyms": []
          }
        ],
        "phonetics": [
          "/faʊl/"
        ]
      },
      {
        "meanings": [
          {
            "antonyms": [],
            "definitions": [
              {
                "definition": "Foul",
                "example": null
              }
            ],
            "part_of_speech": "adjective",
            "synonyms": []
          }
        ],
        "phonetics": []
      }
    ],
    "photo": "fowl_05122024.jpg",
    "word": "fowl"
  },
  {
    "audio": null,
    "categories": [
      "types_of_building"
    ],
    "level": [
      "C2"
    ],
    "materials": [
      {
        "meanings": [
          {
            "antonyms": [],
            "definitions": [
              {
                "definition": "A round building, usually small, often with a dome",
                "example": null
              },
              {
                "definition": "(frequently capitalized) A Gothic typeface used in early printed books in Northern Italy, based on a rounded script developed in the 13th cent.; the manuscript hand on which this typeface was based",
                "example": null
              },
              {
                "definition": "A roundabout; a road junction at which traffic streams circularly around a central island.",
                "example": null
              }
            ],
            "part_of_speech": "noun",
            "synonyms": []
          }
        ],
        "phonetics": [
          "/ɹə(ʊ)ˈtʌndə/",
          "/ɹoʊˈtʌndə/"
        ]
      }
    ],
    "photo": "rotunda_05122024.jpg",
    "word": "rotunda"
  },
  {
    "audio": [
      "clergy_358_05_12_2024.mp3"
    ],
    "categories": [
      "religious_people"
    ],
    "level": [
      "C2"
    ],
    "materials": [
      {
        "meanings": [
          {
            "antonyms": [],
            "definitions": [
              {
                "definition": "Body of persons, such as ministers, sheiks, priests and rabbis, who are trained and ordained for religious service.",
                "example": "Today we brought together clergy from the Wiccan, Christian, New Age and Islamic traditions for an interfaith dialogue."
              }
            ],
            "part_of_speech": "noun",
            "synonyms": []
          }
        ],
        "phonetics": [
          "/ˈklɝdʒi/",
          "/ˈklɜːdʒi/"
        ]
      }
    ],
    "photo": "clergy_05122024.jpg",
    "word": "clergy"
  },
  {
    "audio": [
      "bring round_505_05_12_2024.mp3"
    ],
    "categories": [
      "persuasion"
    ],
    "level": [
      "C2"
    ],
    "materials": [
      {
        "meanings": [
          {
            "antonyms": [],
            "definitions": [
              {
                "definition": "To bring something when coming.",
                "example": "Can you bring round some beer when you come tonight?"
              },
              {
                "definition": "To resuscitate; to cause to regain consciousness.",
                "example": "We thought he was going to die, but the doctors managed to bring him round."
              },
              {
                "definition": "To change someone's opinion or point of view.",
                "example": "She was opposed to the new housing development, but we eventually brought her round."
              }
            ],
            "part_of_speech": "verb",
            "synonyms": [
              "revive",
              "wake up",
              "influence",
              "persuade"
            ]
          }
        ],
        "phonetics": []
      }
    ],
    "photo": "bring_round_05122024.jpg",
    "word": "bring round"
  },
  {
    "audio": null,
    "categories": [
      "political_views_and_systems"
    ],
    "level": [
      "C2"
    ],
    "materials": [
      {
        "meanings": [
          {
            "antonyms": [],
            "definitions": [
              {
                "definition": "An advocate of collectivism.",
                "example": null
              }
            ],
            "part_of_speech": "noun",
            "synonyms": []
          },
          {
            "antonyms": [],
            "definitions": [
              {
                "definition": "Of or pertaining to collectivism.",
                "example": null
              }
            ],
            "part_of_speech": "adjective",
            "synonyms": []
          }
        ],
        "phonetics": [
          "/kəˈlɛktɪvɪst/"
        ]
      }
    ],
    "photo": null,
    "word": "collectivist"
  },
  {
    "audio": [
      "steak_582_05_12_2024.mp3"
    ],
    "categories": [
      "meat_fish_and_seafood"
    ],
    "level": [
      "B1"
    ],
    "materials": [
      {
        "meanings": [
          {
            "antonyms": [],
            "definitions": [
              {
                "definition": "Beefsteak, a slice of beef, broiled or cut for broiling.",
                "example": null
              },
              {
                "definition": "(by extension) A relatively large, thick slice or slab cut from another animal, a vegetable, etc.",
                "example": null
              },
              {
                "definition": "(seafood) A slice of meat cut across the grain (perpendicular to the spine) from a fish.",
                "example": null
              }
            ],
            "part_of_speech": "noun",
            "synonyms": []
          },
          {
            "antonyms": [],
            "definitions": [
              {
                "definition": "To cook (something, especially fish) like or as a steak.",
                "example": null
              }
            ],
            "part_of_speech": "verb",
            "synonyms": []
          }
        ],
        "phonetics": [
          "/steɪk/"
        ]
      }
    ],
    "photo": "steak_05122024.jpg",
    "word": "steak"
  },
  {
    "audio": [
      "shattered_751_05_12_2024.mp3"
    ],
    "categories": [
      "tiredness"
    ],
    "level": [
      "C1"
    ],
    "materials": [
      {
        "meanings": [
          {
            "antonyms": [],
            "definitions": [
              {
                "definition": "To violently break something into pieces.",
                "example": "The miners used dynamite to shatter rocks."
              },
              {
                "definition": "To destroy or disable something.",
                "example": null
              },
              {
                "definition": "To smash, or break into tiny pieces.",
                "example": null
              },
              {
                "definition": "To dispirit or emotionally defeat",
                "example": "to be shattered in intellect; to have shattered hopes, or a shattered constitution"
              },
              {
                "definition": "To scatter about.",
                "example": null
              }
            ],
            "part_of_speech": "verb",
            "synonyms": []
          },
          {
            "antonyms": [],
            "definitions": [
              {
                "definition": "Physically broken into pieces",
                "example": null
              },
              {
                "definition": "Emotionally defeated or dispirited",
                "example": null
              },
              {
                "definition": "Extremely tired or exhausted",
                "example": "I stayed up all night working, and now I'm completely shattered."
              }
            ],
            "part_of_speech": "adjective",
            "synonyms": []
          }
        ],
        "phonetics": [
          "/ˈʃætəd/",
          "/ˈʃætɚd/"
        ]
      }
    ],
    "photo": "shattered_05122024.jpg",
    "word": "shattered"
  },
  {
    "audio": null,
    "categories": [
      "poverty_and_famine"
    ],
    "level": [
      "C2"
    ],
    "materials": [
      {
        "meanings": [
          {
            "antonyms": [],
            "definitions": [
              {
                "definition": "An inquiry into the financial position of a person applying for some form of financial assistance in order to determine their eligibility.",
                "example": null
              }
            ],
            "part_of_speech": "noun",
            "synonyms": []
          },
          {
            "antonyms": [],
            "definitions": [
              {
                "definition": "To apply a means test to an individual or group.",
                "example": null
              }
            ],
            "part_of_speech": "verb",
            "synonyms": []
          }
        ],
        "phonetics": []
      }
    ],
    "photo": "means_test_05122024.jpg",
    "word": "means test"
  },
  {
    "audio": null,
    "categories": [
      "describing_weather"
    ],
    "level": [
      "C2"
    ],
    "materials": [
      {
        "meanings": [
          {
            "antonyms": [],
            "definitions": [
              {
                "definition": "Suggestive or characteristic of winter; cold, stormy.",
                "example": "wintry weather"
              },
              {
                "definition": "Of precipitation, containing sleet or snow.",
                "example": "It will be cloudy overnight, with outbreaks of heavy rain at times. The rain may turn wintry over higher ground."
              },
              {
                "definition": "Aged, white-haired.",
                "example": null
              },
              {
                "definition": "Chilling, cheerless.",
                "example": "a wintry remark"
              }
            ],
            "part_of_speech": "adjective",
            "synonyms": [
              "brumal",
              "hibernal",
              "hiemal"
            ]
          }
        ],
        "phonetics": [
          "/ˈwɪnt(ə)ɹɪ/",
          "/ˈwɪnt(ə)ɹi/"
        ]
      }
    ],
    "photo": "wintry_05122024.jpg",
    "word": "wintry"
  },
  {
    "audio": null,
    "categories": [
      "birds"
    ],
    "level": [
      "C2"
    ],
    "materials": [
      {
        "meanings": [
          {
            "antonyms": [],
            "definitions": [
              {
                "definition": "A small falcon, Falco sparverius, the American kestrel or American sparrowhawk, that preys on grasshoppers and small animals, which is found in North and South America.",
                "example": null
              }
            ],
            "part_of_speech": "noun",
            "synonyms": []
          },
          {
            "antonyms": [],
            "definitions": [
              {
                "definition": "The Eurasian sparrowhawk, Accipiter nisus, a small, short-winged European hawk that preys on smaller birds.",
                "example": null
              },
              {
                "definition": "A female such bird, a male being a musket.",
                "example": null
              },
              {
                "definition": "Any of numerous other species of Accipiter, that prey on smaller birds or otherwise resemble A. nisus.",
                "example": null
              }
            ],
            "part_of_speech": "noun",
            "synonyms": []
          }
        ],
        "phonetics": []
      }
    ],
    "photo": "sparrowhawk_05122024.jpg",
    "word": "sparrowhawk"
  },
  {
    "audio": null,
    "categories": [
      "tennis"
    ],
    "level": [
      "C2"
    ],
    "materials": [
      {
        "meanings": [
          {
            "antonyms": [],
            "definitions": [
              {
                "definition": "A situation where if one of the two players wins the next point, (s)he will win the set (but not the match).",
                "example": null
              },
              {
                "definition": "A setting or location that is fixed.",
                "example": null
              }
            ],
            "part_of_speech": "noun",
            "synonyms": [
              "set ball"
            ]
          }
        ],
        "phonetics": []
      }
    ],
    "photo": "set_point_05122024.jpg",
    "word": "set point"
  },
  {
    "audio": null,
    "categories": [
      "resulting_in_failure",
      "motoring_problems_and_accidents"
    ],
    "level": [
      "C2"
    ],
    "materials": [
      {
        "meanings": [
          {
            "antonyms": [],
            "definitions": [
              {
                "definition": "An act of misfiring.",
                "example": null
              }
            ],
            "part_of_speech": "noun",
            "synonyms": []
          },
          {
            "antonyms": [],
            "definitions": [
              {
                "definition": "To fail to discharge properly.",
                "example": null
              },
              {
                "definition": "(of an engine) To fail to ignite in the proper sequence.",
                "example": null
              },
              {
                "definition": "(by extension) To fail to achieve the anticipated result.",
                "example": "His practical joke misfired and he nearly burnt my left hand."
              }
            ],
            "part_of_speech": "verb",
            "synonyms": []
          }
        ],
        "phonetics": [
          "/ˈmɪsˌfaɪɹ/"
        ]
      }
    ],
    "photo": "misfire_05122024.jpg",
    "word": "misfire"
  },
  {
    "audio": null,
    "categories": [
      "parts_of_a_car"
    ],
    "level": [
      "B1"
    ],
    "materials": [
      {
        "meanings": [
          {
            "antonyms": [],
            "definitions": [
              {
                "definition": "A seat in a motor car.",
                "example": null
              },
              {
                "definition": "A detachable motor car seat equipped with a harness to secure a young child.",
                "example": null
              }
            ],
            "part_of_speech": "noun",
            "synonyms": []
          }
        ],
        "phonetics": []
      }
    ],
    "photo": "car_seat_05122024.jpg",
    "word": "car seat"
  },
  {
    "audio": null,
    "categories": [
      "alcoholic_drinks"
    ],
    "level": [
      "C2"
    ],
    "materials": [
      {
        "meanings": [
          {
            "antonyms": [],
            "definitions": [
              {
                "definition": "A whiskey distilled from a mixture of grains in which at least 51% is corn, aged in charred, new oak barrels. Made in the United States.",
                "example": null
              },
              {
                "definition": "A serving of bourbon whiskey.",
                "example": null
              },
              {
                "definition": "A Bourbon biscuit.",
                "example": null
              }
            ],
            "part_of_speech": "noun",
            "synonyms": [
              "Bourbon whiskey",
              "bourbon whiskey"
            ]
          }
        ],
        "phonetics": []
      }
    ],
    "photo": "bourbon_05122024.jpg",
    "word": "bourbon"
  },
  {
    "audio": null,
    "categories": [
      "other_geographic_features"
    ],
    "level": [
      "B1"
    ],
    "materials": [
      {
        "meanings": [
          {
            "antonyms": [],
            "definitions": [
              {
                "definition": "Land that is suitable for farming and agricultural production.",
                "example": null
              }
            ],
            "part_of_speech": "noun",
            "synonyms": []
          }
        ],
        "phonetics": [
          "/ˈfɑːɹmlænd/",
          "/ˈfɑːmlænd/"
        ]
      }
    ],
    "photo": "farmland_05122024.jpg",
    "word": "farmland"
  },
  {
    "audio": [
      "spasmodic_017_05_12_2024.mp3"
    ],
    "categories": [
      "time_periods"
    ],
    "level": [
      "C2"
    ],
    "materials": [
      {
        "meanings": [
          {
            "antonyms": [],
            "definitions": [
              {
                "definition": "A medicine for suppressing spasms.",
                "example": null
              }
            ],
            "part_of_speech": "noun",
            "synonyms": [
              "antispasmodic"
            ]
          },
          {
            "antonyms": [],
            "definitions": [
              {
                "definition": "Of or relating to a spasm; resembling a sudden contraction of the muscles.",
                "example": null
              },
              {
                "definition": "Convulsive; consisting of spasms.",
                "example": "spasmodic asthma"
              },
              {
                "definition": "Intermittent or fitful; occurring in abrupt bursts.",
                "example": "spasmodic zeal or industry"
              },
              {
                "definition": "Erratic or unsustained.",
                "example": null
              },
              {
                "definition": "Of or relating to the spasmodic poets, a group of British Victorian poets who wrote introspective drama in verse.",
                "example": null
              }
            ],
            "part_of_speech": "adjective",
            "synonyms": [
              "patchy",
              "stop-start"
            ]
          }
        ],
        "phonetics": [
          "/spæzˈmɒd.ɪk/",
          "/spæzˈmɑ.dɪk/"
        ]
      }
    ],
    "photo": "spasmodic_05122024.jpg",
    "word": "spasmodic"
  },
  {
    "audio": null,
    "categories": [
      "cause_and_effect"
    ],
    "level": [
      "C2"
    ],
    "materials": [
      {
        "meanings": [
          {
            "antonyms": [
              "inconsequential"
            ],
            "definitions": [
              {
                "definition": "Following as a result.",
                "example": null
              },
              {
                "definition": "Having significant consequences; of importance.",
                "example": null
              },
              {
                "definition": "Important or significant.",
                "example": null
              },
              {
                "definition": "(of a person) Self-important.",
                "example": null
              }
            ],
            "part_of_speech": "adjective",
            "synonyms": [
              "considerable",
              "important"
            ]
          }
        ],
        "phonetics": [
          "/ˌkɑnsəˈkwɛnʃəl/",
          "/ˌkɒnsəˈkwɛnʃəl/"
        ]
      }
    ],
    "photo": "consequential_05122024.jpg",
    "word": "consequential"
  },
  {
    "audio": [
      "digger_067_05_12_2024.mp3"
    ],
    "categories": [
      "construction"
    ],
    "level": [
      "B2"
    ],
    "materials": [
      {
        "meanings": [
          {
            "antonyms": [],
            "definitions": [
              {
                "definition": "A large piece of machinery that digs holes or trenches; an excavator.",
                "example": null
              },
              {
                "definition": "A tool for digging.",
                "example": null
              },
              {
                "definition": "A spade (playing card).",
                "example": null
              },
              {
                "definition": "One who digs.",
                "example": null
              },
              {
                "definition": "A gold miner, one who digs for gold.",
                "example": null
              },
              {
                "definition": "An informal nickname for a friend; used as a term of endearment.",
                "example": null
              },
              {
                "definition": "An Australian soldier.",
                "example": null
              }
            ],
            "part_of_speech": "noun",
            "synonyms": []
          }
        ],
        "phonetics": [
          "/ˈdɪɡɚ/",
          "/ˈdɪɡə/"
        ]
      }
    ],
    "photo": "digger_05122024.jpg",
    "word": "digger"
  },
  {
    "audio": [
      "taupe_126_05_12_2024.mp3"
    ],
    "categories": [
      "colours"
    ],
    "level": [
      "C2"
    ],
    "materials": [
      {
        "meanings": [
          {
            "antonyms": [],
            "definitions": [
              {
                "definition": "A dark brownish-grey colour, the colour of moleskin.",
                "example": null
              }
            ],
            "part_of_speech": "noun",
            "synonyms": []
          },
          {
            "antonyms": [],
            "definitions": [
              {
                "definition": "Of a dark brownish-grey colour.",
                "example": null
              }
            ],
            "part_of_speech": "adjective",
            "synonyms": []
          }
        ],
        "phonetics": [
          "/təʊp/",
          "/toʊp/"
        ]
      }
    ],
    "photo": "taupe_05122024.jpg",
    "word": "taupe"
  },
  {
    "audio": null,
    "categories": [
      "the_power_industry"
    ],
    "level": [
      "C1"
    ],
    "materials": [
      {
        "meanings": [
          {
            "antonyms": [],
            "definitions": [
              {
                "definition": "A hole drilled into the earth from which petroleum is pumped.",
                "example": null
              }
            ],
            "part_of_speech": "noun",
            "synonyms": []
          }
        ],
        "phonetics": []
      }
    ],
    "photo": "oil_well_05122024.jpg",
    "word": "oil well"
  },
  {
    "audio": [
      "drape_537_05_12_2024.mp3"
    ],
    "categories": [
      "interior_decor"
    ],
    "level": [
      "C2"
    ],
    "materials": [
      {
        "meanings": [
          {
            "antonyms": [],
            "definitions": [
              {
                "definition": "A curtain; a drapery.",
                "example": null
              },
              {
                "definition": "The way in which fabric falls or hangs.",
                "example": null
              },
              {
                "definition": "A member of a youth subculture distinguished by its sharp dress, especially peg-leg pants (1950s: e.g. Baltimore, MD). Antonym: square",
                "example": null
              },
              {
                "definition": "A dress made from an entire piece of cloth, without having pieces cut away as in a fitted garment.",
                "example": null
              }
            ],
            "part_of_speech": "noun",
            "synonyms": []
          },
          {
            "antonyms": [],
            "definitions": [
              {
                "definition": "To cover or adorn with drapery or folds of cloth, or as with drapery",
                "example": "to drape a bust, a building, etc."
              },
              {
                "definition": "To spread over, cover.",
                "example": "I draped my towel over the radiator to dry."
              },
              {
                "definition": "To rail at; to banter.",
                "example": null
              },
              {
                "definition": "To make cloth.",
                "example": null
              },
              {
                "definition": "To design drapery, arrange its folds, etc., as for hangings, costumes, statues, etc.",
                "example": null
              },
              {
                "definition": "To hang or rest limply",
                "example": null
              }
            ],
            "part_of_speech": "verb",
            "synonyms": []
          }
        ],
        "phonetics": [
          "/dɹeɪp/"
        ]
      }
    ],
    "photo": "drape_05122024.jpg",
    "word": "drape"
  },
  {
    "audio": null,
    "categories": [
      "people_in_film_and_theatre"
    ],
    "level": [
      "C2"
    ],
    "materials": [
      {
        "meanings": [
          {
            "antonyms": [],
            "definitions": [
              {
                "definition": "A person who supplies or designs costumes.",
                "example": null
              }
            ],
            "part_of_speech": "noun",
            "synonyms": []
          }
        ],
        "phonetics": []
      }
    ],
    "photo": null,
    "word": "costumier"
  },
  {
    "audio": [
      "elk_902_05_12_2024.mp3"
    ],
    "categories": [
      "wild_mammals"
    ],
    "level": [
      "C2"
    ],
    "materials": [
      {
        "meanings": [
          {
            "antonyms": [],
            "definitions": [
              {
                "definition": "Any of various large species of deer such as the red deer, moose or wapiti (see usage notes).",
                "example": null
              }
            ],
            "part_of_speech": "noun",
            "synonyms": [
              "moose",
              "wapiti"
            ]
          }
        ],
        "phonetics": [
          "/ɛlk/"
        ]
      },
      {
        "meanings": [
          {
            "antonyms": [],
            "definitions": [
              {
                "definition": "The European wild, whistling, or common swan (Cygnus cygnus, syn. Cygnus ferus).",
                "example": null
              }
            ],
            "part_of_speech": "noun",
            "synonyms": []
          }
        ],
        "phonetics": [
          "/ɛlk/"
        ]
      }
    ],
    "photo": "elk_05122024.jpg",
    "word": "elk"
  },
  {
    "audio": [
      "cloudburst_880_05_12_2024.mp3"
    ],
    "categories": [
      "rain"
    ],
    "level": [
      "C2"
    ],
    "materials": [
      {
        "meanings": [
          {
            "antonyms": [],
            "definitions": [
              {
                "definition": "A sudden heavy rainstorm.",
                "example": null
              }
            ],
            "part_of_speech": "noun",
            "synonyms": [
              "cloudbust"
            ]
          }
        ],
        "phonetics": [
          "/ˈklaʊdˌbɝst/",
          "/ˈklaʊdˌbɜːst/"
        ]
      }
    ],
    "photo": "cloudburst_05122024.jpg",
    "word": "cloudburst"
  },
  {
    "audio": null,
    "categories": [
      "pieces_of_music"
    ],
    "level": [
      "C2"
    ],
    "materials": [
      {
        "meanings": [
          {
            "antonyms": [],
            "definitions": [
              {
                "definition": "A song, often sentimental, lamenting an unrequited love; normally sung by a woman.",
                "example": null
              }
            ],
            "part_of_speech": "noun",
            "synonyms": []
          }
        ],
        "phonetics": []
      }
    ],
    "photo": "torch_song_05122024.jpg",
    "word": "torch song"
  },
  {
    "audio": null,
    "categories": [
      "the_car_industry"
    ],
    "level": [
      "C2"
    ],
    "materials": [
      {
        "meanings": [
          {
            "antonyms": [],
            "definitions": [
              {
                "definition": "A trial or practice run of a piece of equipment in its intended usage environment to check for errors before final deployment.",
                "example": null
              },
              {
                "definition": "A test which assesses the performance of an engine or vehicle on the road.",
                "example": null
              },
              {
                "definition": "A driving test.",
                "example": null
              }
            ],
            "part_of_speech": "noun",
            "synonyms": []
          }
        ],
        "phonetics": []
      }
    ],
    "photo": "road_test_05122024.jpg",
    "word": "road test"
  },
  {
    "audio": null,
    "categories": [
      "parts_of_boats"
    ],
    "level": [
      "C2"
    ],
    "materials": [
      {
        "meanings": [
          {
            "antonyms": [],
            "definitions": [
              {
                "definition": "Mizzenmast.",
                "example": null
              },
              {
                "definition": "A fore-and-aft sail set on a mizzenmast.",
                "example": null
              }
            ],
            "part_of_speech": "noun",
            "synonyms": []
          },
          {
            "antonyms": [],
            "definitions": [
              {
                "definition": "Hindmost; nearest the stern.",
                "example": "the mizzen shrouds, sails, etc."
              }
            ],
            "part_of_speech": "adjective",
            "synonyms": []
          }
        ],
        "phonetics": [
          "/ˈmɪ.zən/"
        ]
      }
    ],
    "photo": "mizzen_05122024.jpg",
    "word": "mizzen"
  },
  {
    "audio": null,
    "categories": [
      "complementary_medicine"
    ],
    "level": [
      "C2"
    ],
    "materials": [
      {
        "meanings": [
          {
            "antonyms": [],
            "definitions": [
              {
                "definition": "A form of massage, using the thumbs and palms, employed as therapy.",
                "example": null
              }
            ],
            "part_of_speech": "noun",
            "synonyms": []
          }
        ],
        "phonetics": [
          "/ʃiːˈæt.suː/"
        ]
      }
    ],
    "photo": "shiatsu_05122024.jpg",
    "word": "shiatsu"
  },
  {
    "audio": [
      "grease monkey_207_05_12_2024.mp3"
    ],
    "categories": [
      "people_in_motoring"
    ],
    "level": [
      "C2"
    ],
    "materials": [
      {
        "meanings": [
          {
            "antonyms": [],
            "definitions": [
              {
                "definition": "A mechanic, often with the specific connotation of an automobile mechanic.",
                "example": null
              }
            ],
            "part_of_speech": "noun",
            "synonyms": []
          }
        ],
        "phonetics": []
      }
    ],
    "photo": "grease_monkey_05122024.jpg",
    "word": "grease monkey"
  },
  {
    "audio": null,
    "categories": [
      "achieving_success"
    ],
    "level": [
      "C2"
    ],
    "materials": [
      {
        "meanings": [
          {
            "antonyms": [],
            "definitions": [
              {
                "definition": "To work; to be successful; to solve a problem; to be sufficient or adequate to fulfill a purpose.",
                "example": null
              }
            ],
            "part_of_speech": "verb",
            "synonyms": [
              "do the job",
              "hit the mark"
            ]
          }
        ],
        "phonetics": []
      }
    ],
    "photo": "do_the_job_05122024.jpg",
    "word": "do the job"
  },
  {
    "audio": [
      "bump_279_05_12_2024.mp3"
    ],
    "categories": [
      "injuries",
      "motoring_problems_and_accidents",
      "plane_travel"
    ],
    "level": [
      "C1",
      "C2",
      "B2"
    ],
    "materials": [
      {
        "meanings": [
          {
            "antonyms": [],
            "definitions": [
              {
                "definition": "A light blow or jolting collision.",
                "example": null
              },
              {
                "definition": "The sound of such a collision.",
                "example": null
              },
              {
                "definition": "A protuberance on a level surface.",
                "example": null
              },
              {
                "definition": "A swelling on the skin caused by illness or injury.",
                "example": null
              },
              {
                "definition": "One of the protuberances on the cranium which, in phrenology, are associated with distinct faculties or affections of the mind. Also (metonymically) the faculty itself",
                "example": "the bump of veneration; the bump of acquisitiveness"
              },
              {
                "definition": "The point, in a race in which boats are spaced apart at the start, at which a boat begins to overtake the boat ahead.",
                "example": null
              },
              {
                "definition": "The swollen abdomen of a pregnant woman.",
                "example": null
              },
              {
                "definition": "A post in an Internet forum thread made in order to raise the thread's profile by returning it to the top of the list of active threads.",
                "example": null
              },
              {
                "definition": "A temporary increase in a quantity, as shown in a graph.",
                "example": "US presidential nominees get a post-convention bump in survey ratings."
              },
              {
                "definition": "A dose of a drug such as ketamine or cocaine, when snorted recreationally.",
                "example": null
              },
              {
                "definition": "The noise made by the bittern; a boom.",
                "example": null
              },
              {
                "definition": "(preceded by definite article) A disco dance in which partners rhythmically bump each other's hips together.",
                "example": null
              },
              {
                "definition": "In skipping, a single jump over two consecutive turns of the rope.",
                "example": null
              },
              {
                "definition": "A coarse cotton fabric.",
                "example": null
              },
              {
                "definition": "A training match for a fighting dog.",
                "example": null
              },
              {
                "definition": "The jaw of either of the middle pockets.",
                "example": null
              },
              {
                "definition": "Music, especially played over speakers at loud volume with strong bass frequency response.",
                "example": null
              }
            ],
            "part_of_speech": "noun",
            "synonyms": []
          },
          {
            "antonyms": [],
            "definitions": [
              {
                "definition": "To knock against or run into with a jolt.",
                "example": null
              },
              {
                "definition": "To move up or down by a step; displace.",
                "example": "I bumped the font size up to make my document easier to read."
              },
              {
                "definition": "To post in an Internet forum thread in order to raise the thread's profile by returning it to the top of the list of active threads.",
                "example": null
              },
              {
                "definition": "(of a superheated liquid) To suddenly boil, causing movement of the vessel and loss of liquid.",
                "example": null
              },
              {
                "definition": "To move (a booked passenger) to a later flight because of earlier delays or cancellations.",
                "example": null
              },
              {
                "definition": "To move the time of (a scheduled event).",
                "example": null
              },
              {
                "definition": "To pick (a lock) with a repeated striking motion that dislodges the pins.",
                "example": null
              },
              {
                "definition": "To make a loud, heavy, or hollow noise; to boom.",
                "example": null
              },
              {
                "definition": "To spread out material so as to fill any desired number of pages.",
                "example": null
              }
            ],
            "part_of_speech": "verb",
            "synonyms": []
          }
        ],
        "phonetics": [
          "/bʌmp/"
        ]
      }
    ],
    "photo": "bump_05122024.jpg",
    "word": "bump"
  },
  {
    "audio": null,
    "categories": [
      "skin"
    ],
    "level": [
      "C2"
    ],
    "materials": [
      {
        "meanings": [
          {
            "antonyms": [],
            "definitions": [
              {
                "definition": "To apply ink to; to cover or smear with ink.",
                "example": null
              },
              {
                "definition": "To sign (a contract or similar document).",
                "example": null
              },
              {
                "definition": "To apply a tattoo to (someone).",
                "example": null
              },
              {
                "definition": "(of a squid or octopus) to eject ink (sense 3)",
                "example": null
              }
            ],
            "part_of_speech": "verb",
            "synonyms": [
              "endorse",
              "initial",
              "inscribe",
              "subscribe"
            ]
          },
          {
            "antonyms": [],
            "definitions": [
              {
                "definition": "An application of ink.",
                "example": null
              },
              {
                "definition": "Work done by an inker, one kind of commercial artist",
                "example": null
              },
              {
                "definition": "Inputting text or drawings into a computer, tablet, or similar apparatus using a stylus.",
                "example": null
              },
              {
                "definition": "A defensive activity where ink is released by squids, cuttlefish, etc.",
                "example": null
              }
            ],
            "part_of_speech": "noun",
            "synonyms": []
          }
        ],
        "phonetics": []
      }
    ],
    "photo": "inking_05122024.jpg",
    "word": "inking"
  },
  {
    "audio": null,
    "categories": [
      "prison"
    ],
    "level": [
      "C2"
    ],
    "materials": [
      {
        "meanings": [
          {
            "antonyms": [],
            "definitions": [
              {
                "definition": "An inn or place of call midway on a journey.",
                "example": null
              },
              {
                "definition": "A temporary residence for those who have left prison, residential drug rehabilitation or the like, designed to ease them back into society.",
                "example": null
              }
            ],
            "part_of_speech": "noun",
            "synonyms": []
          }
        ],
        "phonetics": []
      }
    ],
    "photo": "halfway_house_05122024.jpg",
    "word": "halfway house"
  },
  {
    "audio": null,
    "categories": [
      "rank_and_status"
    ],
    "level": [
      "C1"
    ],
    "materials": [
      {
        "meanings": [
          {
            "antonyms": [],
            "definitions": [
              {
                "definition": "A social and economic class lying above the lower class and below the upper middle class.",
                "example": null
              }
            ],
            "part_of_speech": "noun",
            "synonyms": []
          }
        ],
        "phonetics": []
      }
    ],
    "photo": "lower_middle_class_05122024.jpg",
    "word": "lower middle class"
  },
  {
    "audio": [
      "parachute_591_05_12_2024.mp3"
    ],
    "categories": [
      "extreme_sports",
      "plane_travel"
    ],
    "level": [
      "B2"
    ],
    "materials": [
      {
        "meanings": [
          {
            "antonyms": [],
            "definitions": [
              {
                "definition": "A device, generally constructed from fabric, that is designed to employ air resistance to control the fall of an object.",
                "example": null
              },
              {
                "definition": "A web or fold of skin extending between the legs of gliding mammals, such as the flying squirrel and colugo.",
                "example": null
              },
              {
                "definition": "(BDSM) A small collar which fastens around the scrotum and from which weights can be hung.",
                "example": null
              }
            ],
            "part_of_speech": "noun",
            "synonyms": []
          },
          {
            "antonyms": [],
            "definitions": [
              {
                "definition": "To jump, fall, descend, etc. using such a device.",
                "example": null
              },
              {
                "definition": "To introduce into a place using such a device.",
                "example": "The soldiers were parachuted behind enemy lines."
              },
              {
                "definition": "To place (somebody) in an organisation in a position of authority without their having previous experience there; used with in or into.",
                "example": null
              }
            ],
            "part_of_speech": "verb",
            "synonyms": []
          }
        ],
        "phonetics": [
          "/ˈpæɹəʃuːt/"
        ]
      }
    ],
    "photo": "parachute_05122024.jpg",
    "word": "parachute"
  },
  {
    "audio": [
      "peafowl_524_05_12_2024.mp3"
    ],
    "categories": [
      "birds"
    ],
    "level": [
      "C2"
    ],
    "materials": [
      {
        "meanings": [
          {
            "antonyms": [],
            "definitions": [
              {
                "definition": "A pheasant of the genus Pavo or Afropavo, notable for the extravagant tails of the males; a peacock (unspecified sex).",
                "example": null
              }
            ],
            "part_of_speech": "noun",
            "synonyms": [
              "peacock"
            ]
          }
        ],
        "phonetics": [
          "/ˈpiːˌfaʊl/"
        ]
      }
    ],
    "photo": "peafowl_05122024.jpg",
    "word": "peafowl"
  },
  {
    "audio": null,
    "categories": [
      "people_in_sea_travel"
    ],
    "level": [
      "C1"
    ],
    "materials": [
      {
        "meanings": [
          {
            "antonyms": [],
            "definitions": [
              {
                "definition": "Someone who owns a ship.",
                "example": null
              }
            ],
            "part_of_speech": "noun",
            "synonyms": []
          }
        ],
        "phonetics": []
      }
    ],
    "photo": null,
    "word": "shipowner"
  },
  {
    "audio": null,
    "categories": [
      "at_the_dining_table"
    ],
    "level": [
      "C1"
    ],
    "materials": [
      {
        "meanings": [
          {
            "antonyms": [],
            "definitions": [
              {
                "definition": "A cushion or stiff material placed on top of a table, underneath a tablecloth.",
                "example": "After putting the leaves in the table and putting on the tablemat and tablecloth, they laid the placemats out."
              }
            ],
            "part_of_speech": "noun",
            "synonyms": []
          }
        ],
        "phonetics": []
      }
    ],
    "photo": "table_mat_05122024.jpg",
    "word": "table mat"
  },
  {
    "audio": null,
    "categories": [
      "beauty_products"
    ],
    "level": [
      "B1"
    ],
    "materials": [
      {
        "meanings": [
          {
            "antonyms": [],
            "definitions": [
              {
                "definition": "A paste, normally used with a toothbrush, for cleaning the teeth.",
                "example": null
              }
            ],
            "part_of_speech": "noun",
            "synonyms": []
          }
        ],
        "phonetics": [
          "/ˈtuːθpeɪst/"
        ]
      }
    ],
    "photo": "toothpaste_05122024.jpg",
    "word": "toothpaste"
  },
  {
    "audio": null,
    "categories": [
      "describing_clothes"
    ],
    "level": [
      "C2"
    ],
    "materials": [
      {
        "meanings": [
          {
            "antonyms": [],
            "definitions": [
              {
                "definition": "To thrust into liquid, or into any penetrable substance; to immerse.",
                "example": "to plunge the body into water"
              },
              {
                "definition": "To cast, stab or throw into some thing, state, condition or action.",
                "example": "to plunge a dagger into the breast;   to plunge a nation into war"
              },
              {
                "definition": "To baptize by immersion.",
                "example": null
              },
              {
                "definition": "To dive, leap or rush (into water or some liquid); to submerge oneself.",
                "example": "he plunged into the river"
              },
              {
                "definition": "To fall or rush headlong into some thing, action, state or condition.",
                "example": "to plunge into debt;   to plunge into controversy"
              },
              {
                "definition": "To pitch or throw oneself headlong or violently forward, as a horse does.",
                "example": null
              },
              {
                "definition": "To bet heavily and recklessly; to risk large sums in gambling.",
                "example": null
              },
              {
                "definition": "To entangle or embarrass (mostly used in past participle).",
                "example": null
              },
              {
                "definition": "To overwhelm, overpower.",
                "example": null
              }
            ],
            "part_of_speech": "verb",
            "synonyms": []
          },
          {
            "antonyms": [],
            "definitions": [
              {
                "definition": "An occurrence of putting or sinking under water or other fluid.",
                "example": null
              },
              {
                "definition": "A headlong violent motion like that of a horse trying to throw its rider.",
                "example": null
              }
            ],
            "part_of_speech": "noun",
            "synonyms": []
          },
          {
            "antonyms": [],
            "definitions": [
              {
                "definition": "That descends steeply.",
                "example": null
              },
              {
                "definition": "Aimed from higher ground, as fire upon an enemy.",
                "example": null
              }
            ],
            "part_of_speech": "adjective",
            "synonyms": []
          }
        ],
        "phonetics": [
          "/ˈplʌndʒɪŋ/"
        ]
      }
    ],
    "photo": "plunging_05122024.jpg",
    "word": "plunging"
  },
  {
    "audio": null,
    "categories": [
      "furniture"
    ],
    "level": [
      "C2"
    ],
    "materials": [
      {
        "meanings": [
          {
            "antonyms": [],
            "definitions": [
              {
                "definition": "Not fixed in any way to a surface. Relying solely on the force of gravity to stay in place",
                "example": null
              },
              {
                "definition": "That stands alone, not supported at either side",
                "example": null
              },
              {
                "definition": "Independent, autonomous",
                "example": null
              }
            ],
            "part_of_speech": "adjective",
            "synonyms": []
          }
        ],
        "phonetics": []
      }
    ],
    "photo": "free-standing_05122024.jpg",
    "word": "free-standing"
  },
  {
    "audio": null,
    "categories": [
      "political_views_and_systems"
    ],
    "level": [
      "C1"
    ],
    "materials": [
      {
        "meanings": [
          {
            "antonyms": [
              "left wing"
            ],
            "definitions": [
              {
                "definition": "The more right-wing faction of a group or party.",
                "example": null
              },
              {
                "definition": "The right-hand side of a sports field.",
                "example": null
              },
              {
                "definition": "The offensive player who plays to the center's right.",
                "example": null
              }
            ],
            "part_of_speech": "noun",
            "synonyms": []
          }
        ],
        "phonetics": []
      }
    ],
    "photo": "right_wing_05122024.jpg",
    "word": "right wing"
  },
  {
    "audio": [
      "internship_356_05_12_2024.mp3"
    ],
    "categories": [
      "describing_jobs",
      "hospitals",
      "job_interviews"
    ],
    "level": [
      "C2",
      "C1"
    ],
    "materials": [
      {
        "meanings": [
          {
            "antonyms": [],
            "definitions": [
              {
                "definition": "A job taken by a student in order to learn a profession or trade.",
                "example": null
              }
            ],
            "part_of_speech": "noun",
            "synonyms": []
          }
        ],
        "phonetics": [
          "/ˈɪntɝnʃɪp/"
        ]
      }
    ],
    "photo": "internship_05122024.jpg",
    "word": "internship"
  },
  {
    "audio": [
      "loot_298_05_12_2024.mp3"
    ],
    "categories": [
      "committing_crime",
      "computer_games"
    ],
    "level": [
      "C2"
    ],
    "materials": [
      {
        "meanings": [
          {
            "antonyms": [],
            "definitions": [
              {
                "definition": "A kind of scoop or ladle, chiefly used to remove the scum from brine-pans in saltworks.",
                "example": null
              }
            ],
            "part_of_speech": "noun",
            "synonyms": []
          }
        ],
        "phonetics": [
          "/luːt/"
        ]
      },
      {
        "meanings": [
          {
            "antonyms": [],
            "definitions": [
              {
                "definition": "The act of plundering.",
                "example": "the loot of an ancient city"
              },
              {
                "definition": "Plunder, booty, especially from a ransacked city.",
                "example": null
              },
              {
                "definition": "Any prize or profit received for free, especially Christmas presents",
                "example": "1956 \"Free Loot for Children\" (LIFE Magazine, 23 April 1956, p. 131)"
              },
              {
                "definition": "Items dropped by defeated enemies.",
                "example": null
              }
            ],
            "part_of_speech": "noun",
            "synonyms": []
          },
          {
            "antonyms": [],
            "definitions": [
              {
                "definition": "To steal, especially as part of war, riot or other group violence.",
                "example": "1833 \"Gunganarian, the leader of the Chooars, continues his system of looting and murder\", The asiatic Journal and monthly register for British India and its Dependencies Black, Parbury & Allen, p. 66."
              },
              {
                "definition": "To steal from.",
                "example": "to loot a temple for valuables"
              },
              {
                "definition": "To examine the corpse of a fallen enemy for loot.",
                "example": null
              }
            ],
            "part_of_speech": "verb",
            "synonyms": []
          }
        ],
        "phonetics": [
          "/luːt/"
        ]
      }
    ],
    "photo": "loot_05122024.jpg",
    "word": "loot"
  },
  {
    "audio": null,
    "categories": [
      "describing_work"
    ],
    "level": [
      "C1"
    ],
    "materials": [
      {
        "meanings": [
          {
            "antonyms": [
              "de-energize",
              "sedate",
              "stifle"
            ],
            "definitions": [
              {
                "definition": "To encourage into action.",
                "example": null
              },
              {
                "definition": "To arouse an organism to functional activity.",
                "example": null
              }
            ],
            "part_of_speech": "verb",
            "synonyms": [
              "animate",
              "arouse",
              "energise",
              "energize",
              "excite",
              "perk up",
              "encourage",
              "incite",
              "induce",
              "provoke"
            ]
          },
          {
            "antonyms": [],
            "definitions": [
              {
                "definition": "Having a manner that stimulates.",
                "example": null
              }
            ],
            "part_of_speech": "adjective",
            "synonyms": []
          }
        ],
        "phonetics": []
      }
    ],
    "photo": "stimulating_05122024.jpg",
    "word": "stimulating"
  },
  {
    "audio": null,
    "categories": [
      "grammar"
    ],
    "level": [
      "C2"
    ],
    "materials": [
      {
        "meanings": [
          {
            "antonyms": [],
            "definitions": [
              {
                "definition": "(grammar, usually plural) Any of the forms of a word which contain its stem(s) in the simplest form, or such a form that, when taken with all the other principal parts, allows the entire paradigm to be derived.",
                "example": null
              },
              {
                "definition": "A polynomial approximation of a power series, made up of monomials whose indices lie in the Newton diagram of the power series and which occur with the same coefficients as in the original power series.",
                "example": null
              },
              {
                "definition": "The portion of a Laurent series that has negative exponents.",
                "example": null
              }
            ],
            "part_of_speech": "noun",
            "synonyms": []
          }
        ],
        "phonetics": []
      }
    ],
    "photo": "principal_parts_05122024.jpg",
    "word": "principal parts"
  },
  {
    "audio": [
      "run-in_863_05_12_2024.mp3"
    ],
    "categories": [
      "having_a_disagreement"
    ],
    "level": [
      "C2"
    ],
    "materials": [
      {
        "meanings": [
          {
            "antonyms": [],
            "definitions": [
              {
                "definition": "An encounter; a scrape or brush, especially one involving trouble or difficulty.",
                "example": null
              },
              {
                "definition": "The end-phase of a competition.",
                "example": "Yahoo Sport's Leicester City blogger Helen Nutter gets ready for the Premier League run-in knowing her side - incredibly - still have a great chance of being crowned champions"
              }
            ],
            "part_of_speech": "noun",
            "synonyms": []
          }
        ],
        "phonetics": []
      }
    ],
    "photo": "run-in_05122024.jpg",
    "word": "run-in"
  },
  {
    "audio": null,
    "categories": [
      "combat_sports"
    ],
    "level": [
      "C1"
    ],
    "materials": [
      {
        "meanings": [
          {
            "antonyms": [],
            "definitions": [
              {
                "definition": "A very large, heavy, or impressive person.",
                "example": "an intellectual heavyweight"
              },
              {
                "definition": "The professional boxing weight class for boxers weighing more than 190 pounds; a boxer in that division.",
                "example": null
              },
              {
                "definition": "(uncountable) A similar division and contestant in other sports.",
                "example": null
              }
            ],
            "part_of_speech": "noun",
            "synonyms": []
          },
          {
            "antonyms": [],
            "definitions": [
              {
                "definition": "Of the heavyweight boxing (or similar) division.",
                "example": null
              },
              {
                "definition": "Being relatively heavy.",
                "example": null
              },
              {
                "definition": "Being a leader in one's field.",
                "example": null
              },
              {
                "definition": "Important or impressive.",
                "example": null
              }
            ],
            "part_of_speech": "adjective",
            "synonyms": []
          }
        ],
        "phonetics": []
      }
    ],
    "photo": "heavyweight_05122024.jpg",
    "word": "heavyweight"
  },
  {
    "audio": null,
    "categories": [
      "preparing_food"
    ],
    "level": [
      "C2"
    ],
    "materials": [
      {
        "meanings": [
          {
            "antonyms": [],
            "definitions": [
              {
                "definition": "A dry leavening agent used in baking; a mixture of baking soda, an acid (often cream of tartar) and starch to keep it dry; when wetted, carbon dioxide is released.",
                "example": null
              }
            ],
            "part_of_speech": "noun",
            "synonyms": []
          }
        ],
        "phonetics": []
      }
    ],
    "photo": "baking_powder_05122024.jpg",
    "word": "baking powder"
  },
  {
    "audio": null,
    "categories": [
      "water_sports",
      "items_of_clothing"
    ],
    "level": [
      "C1"
    ],
    "materials": [
      {
        "meanings": [
          {
            "antonyms": [],
            "definitions": [
              {
                "definition": "A close fitting, insulating garment usually made from neoprene or similar material designed to keep one warm during activities on or under water.",
                "example": null
              }
            ],
            "part_of_speech": "noun",
            "synonyms": []
          }
        ],
        "phonetics": [
          "/ˈwɛtˌs(j)ut/"
        ]
      }
    ],
    "photo": "wetsuit_05122024.jpg",
    "word": "wetsuit"
  },
  {
    "audio": [
      "knocker_807_05_12_2024.mp3"
    ],
    "categories": [
      "parts_of_a_house"
    ],
    "level": [
      "C2"
    ],
    "materials": [
      {
        "meanings": [
          {
            "antonyms": [],
            "definitions": [
              {
                "definition": "A device, usually hinged with a striking plate, used for knocking on a door.",
                "example": null
              },
              {
                "definition": "A person who knocks.",
                "example": null
              },
              {
                "definition": "A critic; one who disparages.",
                "example": null
              },
              {
                "definition": "A person who knocks (denigrates) something.",
                "example": null
              },
              {
                "definition": "(usually in the plural) A woman's breasts.",
                "example": null
              },
              {
                "definition": "(especially Cardigan) A dwarf, goblin, or sprite imagined to dwell in mines and to indicate the presence of ore by knocking.",
                "example": null
              },
              {
                "definition": "A mechanical device in a pinball table that produces a loud percussive noise.",
                "example": null
              },
              {
                "definition": "A person who is strikingly handsome or otherwise admirable; a stunner.",
                "example": null
              },
              {
                "definition": "A large cockroach, especially Blaberus giganteus, of semitropical America, which is able to produce a loud knocking sound.",
                "example": null
              },
              {
                "definition": "A large, boulder-shaped outcrop of bedrock in an otherwise low-lying landscape, chiefly associated with a mélange.",
                "example": null
              },
              {
                "definition": "One who defaults on payment of a wager.",
                "example": null
              }
            ],
            "part_of_speech": "noun",
            "synonyms": []
          }
        ],
        "phonetics": []
      }
    ],
    "photo": "knocker_05122024.jpg",
    "word": "knocker"
  },
  {
    "audio": null,
    "categories": [
      "on_the_road"
    ],
    "level": [
      "C2"
    ],
    "materials": [
      {
        "meanings": [
          {
            "antonyms": [
              "farside",
              "offside"
            ],
            "definitions": [
              {
                "definition": "The side of a road vehicle nearest to the kerb: the left side if one drives on the left of the road.",
                "example": null
              },
              {
                "definition": "The face of the Moon nearest the Earth.",
                "example": null
              },
              {
                "definition": "A streetcar designed to discharge passengers on the near side of an intersection, rather than the far side.",
                "example": null
              }
            ],
            "part_of_speech": "noun",
            "synonyms": []
          }
        ],
        "phonetics": []
      }
    ],
    "photo": null,
    "word": "nearside"
  },
  {
    "audio": null,
    "categories": [
      "pay_and_conditions_at_work"
    ],
    "level": [
      "C2"
    ],
    "materials": [
      {
        "meanings": [
          {
            "antonyms": [],
            "definitions": [
              {
                "definition": "An event in which an employer bars employees from working as a tactic in negotiating terms of employment, particularly in response to a strike or threat to strike.",
                "example": null
              }
            ],
            "part_of_speech": "noun",
            "synonyms": []
          },
          {
            "antonyms": [],
            "definitions": [
              {
                "definition": "To inadvertently prevent (a person, particularly oneself) from entering a place, by leaving it locked.",
                "example": "I've locked myself out of my room again!"
              },
              {
                "definition": "To prevent from accessing a data structure.",
                "example": null
              }
            ],
            "part_of_speech": "verb",
            "synonyms": []
          }
        ],
        "phonetics": []
      }
    ],
    "photo": "lock_out_05122024.jpg",
    "word": "lock out"
  },
  {
    "audio": null,
    "categories": [
      "finance"
    ],
    "level": [
      "C2"
    ],
    "materials": [
      {
        "meanings": [
          {
            "antonyms": [
              "impossibility",
              "inevitability"
            ],
            "definitions": [
              {
                "definition": "The quality of being contingent, of happening by chance; unpredictability.",
                "example": null
              },
              {
                "definition": "A possibility; something which may or may not happen. A chance occurrence, especially in finance, unexpected expenses.",
                "example": null
              },
              {
                "definition": "An amount of money which a party to a contract has to pay to the other party (usually the supplier of a major project to the client) if he or she does not fulfill the contract according to the specification.",
                "example": null
              },
              {
                "definition": "A statement which is neither a tautology nor a contradiction.",
                "example": null
              }
            ],
            "part_of_speech": "noun",
            "synonyms": [
              "possibility"
            ]
          }
        ],
        "phonetics": [
          "/kənˈtɪndʒənsi/"
        ]
      }
    ],
    "photo": "contingency_05122024.jpg",
    "word": "contingency"
  },
  {
    "audio": null,
    "categories": [
      "non_alcoholic_drinks"
    ],
    "level": [
      "C2"
    ],
    "materials": [
      {
        "meanings": [
          {
            "antonyms": [],
            "definitions": [
              {
                "definition": "A refreshing drink flavored with aromatic herbs, especially mint, and sometimes alcohol.",
                "example": null
              },
              {
                "definition": "A pleasant-tasting liquid medicine in which other nauseous medicines are taken.",
                "example": null
              }
            ],
            "part_of_speech": "noun",
            "synonyms": []
          }
        ],
        "phonetics": [
          "/ˈdʒuːlɛp/"
        ]
      }
    ],
    "photo": "julep_05122024.jpg",
    "word": "julep"
  },
  {
    "audio": [
      "iris_351_05_12_2024.mp3"
    ],
    "categories": [
      "plants",
      "face"
    ],
    "level": [
      "C2"
    ],
    "materials": [
      {
        "meanings": [
          {
            "antonyms": [],
            "definitions": [
              {
                "definition": "A plant of the genus Iris, common in the northern hemisphere, and generally having attractive blooms (See Iris (plant)).",
                "example": null
              },
              {
                "definition": "The contractile membrane perforated by the pupil, which adjusts to control the amount of light reaching the retina, and which forms the colored portion of the eye (See Iris (anatomy)).",
                "example": null
              },
              {
                "definition": "A diaphragm used to regulate the size of a hole, especially as a way of controlling the amount of light reaching a lens.",
                "example": null
              },
              {
                "definition": "A rainbow, or other colourful refraction of light.",
                "example": null
              },
              {
                "definition": "A constricted opening in the path inside a waveguide, used to form a resonator.",
                "example": null
              },
              {
                "definition": "The inner circle of an oscillated color spot.",
                "example": null
              }
            ],
            "part_of_speech": "noun",
            "synonyms": []
          },
          {
            "antonyms": [],
            "definitions": [
              {
                "definition": "(of an aperture, lens or door) To open or close in the manner of an iris.",
                "example": null
              }
            ],
            "part_of_speech": "verb",
            "synonyms": []
          }
        ],
        "phonetics": [
          "/ˈaɪɹɪs/"
        ]
      }
    ],
    "photo": "iris_05122024.jpg",
    "word": "iris"
  },
  {
    "audio": null,
    "categories": [
      "describing_clothes"
    ],
    "level": [
      "C1"
    ],
    "materials": [
      {
        "meanings": [
          {
            "antonyms": [
              "opaque",
              "solid"
            ],
            "definitions": [
              {
                "definition": "Transparent or translucent; that can be seen through",
                "example": "If you are planning to wear a see-through dress, wear something underneath."
              }
            ],
            "part_of_speech": "adjective",
            "synonyms": [
              "clear",
              "diaphanous",
              "transparent"
            ]
          }
        ],
        "phonetics": []
      }
    ],
    "photo": "see-through_05122024.jpg",
    "word": "see-through"
  },
  {
    "audio": null,
    "categories": [
      "natural_disasters"
    ],
    "level": [
      "C2"
    ],
    "materials": [
      {
        "meanings": [
          {
            "antonyms": [],
            "definitions": [
              {
                "definition": "An eruptive rock, one produced by eruption.",
                "example": null
              }
            ],
            "part_of_speech": "noun",
            "synonyms": []
          },
          {
            "antonyms": [],
            "definitions": [
              {
                "definition": "That erupts or bursts forth.",
                "example": null
              },
              {
                "definition": "Accompanied by eruptions.",
                "example": "an eruptive fever"
              },
              {
                "definition": "Produced by eruption.",
                "example": "eruptive rocks, such as the igneous or volcanic"
              }
            ],
            "part_of_speech": "adjective",
            "synonyms": []
          }
        ],
        "phonetics": [
          "/ɪˈɹʌptɪv/"
        ]
      }
    ],
    "photo": "eruptive_05122024.jpg",
    "word": "eruptive"
  },
  {
    "audio": null,
    "categories": [
      "buying_a_home"
    ],
    "level": [
      "C2"
    ],
    "materials": [
      {
        "meanings": [
          {
            "antonyms": [],
            "definitions": [
              {
                "definition": "To reduce the offer price of a property after agreeing to a higher one (normally just before contracts are exchanged)",
                "example": null
              }
            ],
            "part_of_speech": "verb",
            "synonyms": []
          }
        ],
        "phonetics": []
      }
    ],
    "photo": null,
    "word": "gazundering"
  },
  {
    "audio": [
      "sinewy_092_05_12_2024.mp3"
    ],
    "categories": [
      "body_shape"
    ],
    "level": [
      "C2"
    ],
    "materials": [
      {
        "meanings": [
          {
            "antonyms": [],
            "definitions": [
              {
                "definition": "Tough; having strong sinews.",
                "example": null
              },
              {
                "definition": "Having or showing nervous strength.",
                "example": null
              },
              {
                "definition": "(of a person or animal) Possessing physical strength and weight; rugged and powerful.",
                "example": null
              }
            ],
            "part_of_speech": "adjective",
            "synonyms": []
          }
        ],
        "phonetics": [
          "/ˈsɪnjuːi/"
        ]
      }
    ],
    "photo": null,
    "word": "sinewy"
  },
  {
    "audio": null,
    "categories": [
      "the_tourist_industry"
    ],
    "level": [
      "C1"
    ],
    "materials": [
      {
        "meanings": [
          {
            "antonyms": [],
            "definitions": [
              {
                "definition": "The act, process, or result of cancelling; as, the cancellation of certain words in a contract, or of the contract itself.",
                "example": null
              },
              {
                "definition": "The operation of striking out common factors, in both the dividend and divisor.",
                "example": null
              },
              {
                "definition": "A postmark that marks a postage stamp so as to prevent its reuse.",
                "example": null
              },
              {
                "definition": "In United States intellectual property law, a proceeding in which an interested party seeks to cancel the registration of a trademark or patent.",
                "example": null
              },
              {
                "definition": "The property of being cancellate.",
                "example": null
              }
            ],
            "part_of_speech": "noun",
            "synonyms": []
          }
        ],
        "phonetics": [
          "/kænsəˈleɪʃən/"
        ]
      }
    ],
    "photo": "cancellation_05122024.jpg",
    "word": "cancellation"
  },
  {
    "audio": [
      "clean up_392_05_12_2024.mp3"
    ],
    "categories": [
      "waste_and_pollution"
    ],
    "level": [
      "B1"
    ],
    "materials": [
      {
        "meanings": [
          {
            "antonyms": [],
            "definitions": [
              {
                "definition": "To make an area or a thing clean; to pick up a mess; to tidy.",
                "example": "Clean up your room."
              },
              {
                "definition": "To become clean, handsome, smart in appearance, e.g. for a special occasion, especially when it is out of character to be seen as such.",
                "example": "He sure cleans up nice."
              },
              {
                "definition": "To make a large profit; to win by a large margin, or to win a large amount, especially in gambling. Also clean house.",
                "example": "Man, he sure cleaned up last night at the blackjack table.   The investors cleaned up when the stock hit the roof last year."
              }
            ],
            "part_of_speech": "verb",
            "synonyms": []
          },
          {
            "antonyms": [],
            "definitions": [
              {
                "definition": "The act of cleaning or tidying something.",
                "example": null
              },
              {
                "definition": "Fourth in the batting order; a cleanup hitter.",
                "example": "Jones will be batting cleanup in tonight's game."
              }
            ],
            "part_of_speech": "noun",
            "synonyms": []
          }
        ],
        "phonetics": []
      }
    ],
    "photo": "clean_up_05122024.jpg",
    "word": "clean up"
  },
  {
    "audio": null,
    "categories": [
      "justice"
    ],
    "level": [
      "C2"
    ],
    "materials": [
      {
        "meanings": [
          {
            "antonyms": [],
            "definitions": [
              {
                "definition": "The conduct of a lawsuit.",
                "example": "That attorney has been chastised for his litigation behavior."
              }
            ],
            "part_of_speech": "noun",
            "synonyms": []
          }
        ],
        "phonetics": [
          "/ˌlɪtəˈɡeɪʃən/"
        ]
      }
    ],
    "photo": "litigation_05122024.jpg",
    "word": "litigation"
  },
  {
    "audio": null,
    "categories": [
      "being_ill"
    ],
    "level": [
      "A2"
    ],
    "materials": [
      {
        "meanings": [
          {
            "antonyms": [],
            "definitions": [
              {
                "definition": "A pain in the middle or inner ear.",
                "example": null
              }
            ],
            "part_of_speech": "noun",
            "synonyms": [
              "otalgia"
            ]
          }
        ],
        "phonetics": [
          "/ˈiɹeɪk/",
          "/ˈɪə̯ɹeɪk/"
        ]
      }
    ],
    "photo": "earache_05122024.jpg",
    "word": "earache"
  },
  {
    "audio": [
      "flared_485_05_12_2024.mp3"
    ],
    "categories": [
      "describing_clothes"
    ],
    "level": [
      "C2"
    ],
    "materials": [
      {
        "meanings": [
          {
            "antonyms": [],
            "definitions": [
              {
                "definition": "To cause to burn.",
                "example": null
              },
              {
                "definition": "To cause inflammation; to inflame.",
                "example": null
              },
              {
                "definition": "To open outward in shape.",
                "example": "The building flared from the third through the seventh floors to occupy the airspace over the entrance plaza. (intransitive)"
              },
              {
                "definition": "To (operate an aircraft to) transition from downward flight to level flight just before landing.",
                "example": null
              },
              {
                "definition": "To blaze brightly.",
                "example": "The blast furnace flared in the night."
              },
              {
                "definition": "To shine out with a sudden and unsteady light; to emit a dazzling or painfully bright light.",
                "example": "The candle flared in a sudden draught."
              },
              {
                "definition": "To shine out with gaudy colours; to be offensively bright or showy.",
                "example": null
              },
              {
                "definition": "To suddenly happen or intensify.",
                "example": null
              },
              {
                "definition": "To suddenly erupt in anger.",
                "example": null
              },
              {
                "definition": "To be exposed to too much light.",
                "example": null
              }
            ],
            "part_of_speech": "verb",
            "synonyms": [
              "flare up",
              "flare up"
            ]
          }
        ],
        "phonetics": []
      }
    ],
    "photo": "flared_05122024.jpg",
    "word": "flared"
  },
  {
    "audio": [
      "bearskin_727_05_12_2024.mp3"
    ],
    "categories": [
      "hats"
    ],
    "level": [
      "C2"
    ],
    "materials": [
      {
        "meanings": [
          {
            "antonyms": [],
            "definitions": [
              {
                "definition": "The pelt of a bear, especially when used as a rug.",
                "example": null
              },
              {
                "definition": "A tall ceremonial hat worn by members of some British regiments for ceremonial occasions; a busby.",
                "example": null
              },
              {
                "definition": "A coarse, shaggy, woollen cloth for overcoats.",
                "example": null
              }
            ],
            "part_of_speech": "noun",
            "synonyms": [
              "busby"
            ]
          }
        ],
        "phonetics": [
          "/ˈbɛə.skɪn/",
          "/ˈbɛəɹ.skɪn/"
        ]
      }
    ],
    "photo": "bearskin_05122024.jpg",
    "word": "bearskin"
  },
  {
    "audio": [
      "appendicitis_920_05_12_2024.mp3"
    ],
    "categories": [
      "types_of_illness"
    ],
    "level": [
      "C2"
    ],
    "materials": [
      {
        "meanings": [
          {
            "antonyms": [],
            "definitions": [
              {
                "definition": "Inflammation of the vermiform appendix",
                "example": null
              }
            ],
            "part_of_speech": "noun",
            "synonyms": []
          }
        ],
        "phonetics": [
          "/əˈpɛnd.ɪ.saɪt.əs/"
        ]
      }
    ],
    "photo": "appendicitis_05122024.jpg",
    "word": "appendicitis"
  },
  {
    "audio": null,
    "categories": [
      "death"
    ],
    "level": [
      "C2"
    ],
    "materials": [
      {
        "meanings": [
          {
            "antonyms": [],
            "definitions": [
              {
                "definition": "A stone slab set at the head of a grave.",
                "example": null
              }
            ],
            "part_of_speech": "noun",
            "synonyms": [
              "headstone",
              "tombstone"
            ]
          }
        ],
        "phonetics": []
      }
    ],
    "photo": "gravestone_05122024.jpg",
    "word": "gravestone"
  },
  {
    "audio": null,
    "categories": [
      "biology"
    ],
    "level": [
      "C2"
    ],
    "materials": [
      {
        "meanings": [
          {
            "antonyms": [],
            "definitions": [
              {
                "definition": "(now specifically) Human and animal solid waste excreted from the bowels; feces.",
                "example": null
              },
              {
                "definition": "Any waste matter excreted from the human or animal body, or discharged by bodily organs.",
                "example": null
              }
            ],
            "part_of_speech": "noun",
            "synonyms": []
          }
        ],
        "phonetics": [
          "/ˈɛkskɹəmənt/"
        ]
      },
      {
        "meanings": [
          {
            "antonyms": [],
            "definitions": [
              {
                "definition": "Something which grows out of the body; hair, nails etc.",
                "example": null
              }
            ],
            "part_of_speech": "noun",
            "synonyms": []
          }
        ],
        "phonetics": [
          "/ˈɛkskɹəmənt/"
        ]
      }
    ],
    "photo": "excrement_05122024.jpg",
    "word": "excrement"
  },
  {
    "audio": null,
    "categories": [
      "artwork_and_techniques"
    ],
    "level": [
      "C2"
    ],
    "materials": [
      {
        "meanings": [
          {
            "antonyms": [],
            "definitions": [
              {
                "definition": "A three-dimensional image of an object created by holography.",
                "example": null
              }
            ],
            "part_of_speech": "noun",
            "synonyms": []
          }
        ],
        "phonetics": []
      }
    ],
    "photo": "hologram_05122024.jpg",
    "word": "hologram"
  },
  {
    "audio": [
      "rudder_465_05_12_2024.mp3"
    ],
    "categories": [
      "parts_of_a_plane"
    ],
    "level": [
      "C2"
    ],
    "materials": [
      {
        "meanings": [
          {
            "antonyms": [],
            "definitions": [
              {
                "definition": "An underwater vane used to steer a vessel. The rudder is controlled by means of a wheel, tiller or other apparatus (modern vessels can be controlled even with a joystick or an autopilot).",
                "example": null
              },
              {
                "definition": "A control surface on the vertical stabilizer of a fixed-wing aircraft or an autogyro. On some craft, the entire vertical stabilizer comprises the rudder. The rudder is controlled by foot-operated control pedals.",
                "example": null
              },
              {
                "definition": "A riddle or sieve.",
                "example": null
              },
              {
                "definition": "That which resembles a rudder as a guide or governor; that which guides or governs the course.",
                "example": null
              }
            ],
            "part_of_speech": "noun",
            "synonyms": []
          }
        ],
        "phonetics": [
          "/ˈɹʌdɚ/",
          "/ˈɹʌdə(ɹ)/"
        ]
      }
    ],
    "photo": "rudder_05122024.jpg",
    "word": "rudder"
  },
  {
    "audio": null,
    "categories": [
      "parts_of_a_building",
      "religious_places"
    ],
    "level": [
      "C2"
    ],
    "materials": [
      {
        "meanings": [
          {
            "antonyms": [],
            "definitions": [
              {
                "definition": "A cave or cavern.",
                "example": null
              },
              {
                "definition": "An underground vault, especially one beneath a church that is used as a burial place.",
                "example": null
              },
              {
                "definition": "A small pit or cavity in the surface of an organ or other structure.",
                "example": null
              }
            ],
            "part_of_speech": "noun",
            "synonyms": []
          }
        ],
        "phonetics": [
          "/kɹɪpt/"
        ]
      }
    ],
    "photo": "crypt_05122024.jpg",
    "word": "crypt"
  },
  {
    "audio": null,
    "categories": [
      "facial_expressions"
    ],
    "level": [
      "C2"
    ],
    "materials": [
      {
        "meanings": [
          {
            "antonyms": [],
            "definitions": [
              {
                "definition": "A contorted facial expression, often expressing contempt or pain.",
                "example": null
              },
              {
                "definition": "Affectation, pretence.",
                "example": null
              }
            ],
            "part_of_speech": "noun",
            "synonyms": []
          },
          {
            "antonyms": [],
            "definitions": [
              {
                "definition": "To make grimaces; to distort one's face; to make faces.",
                "example": null
              }
            ],
            "part_of_speech": "verb",
            "synonyms": []
          }
        ],
        "phonetics": [
          "/ˈɡɹɪm.əs/"
        ]
      }
    ],
    "photo": "grimace_05122024.jpg",
    "word": "grimace"
  },
  {
    "audio": null,
    "categories": [
      "restaurant_people"
    ],
    "level": [
      "B1"
    ],
    "materials": [
      {
        "meanings": [
          {
            "antonyms": [],
            "definitions": [
              {
                "definition": "The member of staff at a restaurant who keeps the wine cellar, advises guests on the choice of wines and serves them.",
                "example": null
              }
            ],
            "part_of_speech": "noun",
            "synonyms": [
              "sommelier",
              "wine steward"
            ]
          }
        ],
        "phonetics": []
      }
    ],
    "photo": "wine_waiter_05122024.jpg",
    "word": "wine waiter"
  },
  {
    "audio": null,
    "categories": [
      "furniture"
    ],
    "level": [
      "C2"
    ],
    "materials": [
      {
        "meanings": [
          {
            "antonyms": [],
            "definitions": [
              {
                "definition": "A cot; a lightweight portable bed used by the military, campers etc.",
                "example": null
              }
            ],
            "part_of_speech": "noun",
            "synonyms": [
              "cot",
              "folding bed"
            ]
          }
        ],
        "phonetics": []
      }
    ],
    "photo": "camp_bed_05122024.jpg",
    "word": "camp bed"
  },
  {
    "audio": null,
    "categories": [
      "tennis"
    ],
    "level": [
      "C2"
    ],
    "materials": [
      {
        "meanings": [
          {
            "antonyms": [],
            "definitions": [
              {
                "definition": "The missing of both the first serve and second serve, resulting in a point for the receiver.",
                "example": null
              },
              {
                "definition": "An exception thrown by the CPU while trying to call the handler of another exception (e.g. the exception handler is invalid or the call stack has overflowed).",
                "example": null
              }
            ],
            "part_of_speech": "noun",
            "synonyms": []
          }
        ],
        "phonetics": []
      }
    ],
    "photo": "double_fault_05122024.jpg",
    "word": "double fault"
  },
  {
    "audio": null,
    "categories": [
      "war"
    ],
    "level": [
      "C2"
    ],
    "materials": [
      {
        "meanings": [
          {
            "antonyms": [],
            "definitions": [
              {
                "definition": "A body of forces equipped for war.",
                "example": null
              },
              {
                "definition": "All the cannon and small arms collectively, with their equipments, belonging to a ship or a fortification.",
                "example": null
              },
              {
                "definition": "Any equipment for resistance.",
                "example": null
              },
              {
                "definition": "The process of building up military capacity.",
                "example": null
              }
            ],
            "part_of_speech": "noun",
            "synonyms": []
          }
        ],
        "phonetics": [
          "/ˈɑː(ɹ)məmənt/"
        ]
      }
    ],
    "photo": "armament_05122024.jpg",
    "word": "armament"
  }
]