[
  {
    "audio": null,
    "categories": [
      "parts_of_a_plane"
    ],
    "level": [
      "C2"
    ],
    "materials": [
      {
        "meanings": [
          {
            "antonyms": [],
            "definitions": [
              {
                "definition": "A type of gas turbine aircraft engine that drives and obtains essentially all thrust from an external (typically unducted) propeller.",
                "example": null
              },
              {
                "definition": "An aircraft that uses a turboprop engine.",
                "example": null
              }
            ],
            "part_of_speech": "noun",
            "synonyms": [
              "propjet"
            ]
          }
        ],
        "phonetics": []
      }
    ],
    "photo": "turboprop_05122024.jpg",
    "word": "turboprop"
  },
  {
    "audio": null,
    "categories": [
      "war"
    ],
    "level": [
      "C2"
    ],
    "materials": [
      {
        "meanings": [
          {
            "antonyms": [
              "accretion"
            ],
            "definitions": [
              {
                "definition": "Wearing or grinding down by friction.",
                "example": null
              },
              {
                "definition": "The gradual reduction in a tangible or intangible resource due to causes that are passive and do not involve productive use of the resource.",
                "example": null
              },
              {
                "definition": "(human resources) A gradual, natural reduction in membership or personnel, as through retirement, resignation, or death.",
                "example": null
              },
              {
                "definition": "The loss of participants during an experiment.",
                "example": null
              },
              {
                "definition": "Imperfect contrition or remorse.",
                "example": null
              },
              {
                "definition": "The wearing of teeth due to their grinding.",
                "example": null
              },
              {
                "definition": "The loss of a first or second language or a portion of that language.",
                "example": null
              }
            ],
            "part_of_speech": "noun",
            "synonyms": [
              "natural wastage"
            ]
          },
          {
            "antonyms": [],
            "definitions": [
              {
                "definition": "To grind or wear down through friction.",
                "example": "attritioned teeth; attritioned rock"
              },
              {
                "definition": "To reduce the number of (jobs or workers) by not hiring new employees to fill positions that become vacant (often with out).",
                "example": "As a result of the new policy, people were being attritioned out."
              },
              {
                "definition": "To undergo a reduction in number.",
                "example": "The cohort of one hundred students had attritioned to sixty by the end of secondary school."
              }
            ],
            "part_of_speech": "verb",
            "synonyms": [
              "attrit"
            ]
          }
        ],
        "phonetics": [
          "[əˈtɹɪʃən]"
        ]
      }
    ],
    "photo": "attrition_05122024.jpg",
    "word": "attrition"
  },
  {
    "audio": null,
    "categories": [
      "family_background"
    ],
    "level": [
      "C2"
    ],
    "materials": [
      {
        "meanings": [
          {
            "antonyms": [],
            "definitions": [
              {
                "definition": "Relation or connection by blood, marriage or adoption",
                "example": null
              },
              {
                "definition": "Relation or connection by nature or character",
                "example": null
              }
            ],
            "part_of_speech": "noun",
            "synonyms": []
          }
        ],
        "phonetics": []
      }
    ],
    "photo": "kinship_05122024.jpg",
    "word": "kinship"
  },
  {
    "audio": null,
    "categories": [
      "computer_games"
    ],
    "level": [
      "C2"
    ],
    "materials": [
      {
        "meanings": [
          {
            "antonyms": [],
            "definitions": [
              {
                "definition": "A video game of the genre characterized by jumping (or otherwise moving) to and from suspended platforms or over obstacles.",
                "example": null
              }
            ],
            "part_of_speech": "noun",
            "synonyms": [
              "platformer"
            ]
          }
        ],
        "phonetics": []
      }
    ],
    "photo": "platform game_05122024.jpg",
    "word": "platform game"
  },
  {
    "audio": null,
    "categories": [
      "birds"
    ],
    "level": [
      "C2"
    ],
    "materials": [
      {
        "meanings": [
          {
            "antonyms": [],
            "definitions": [
              {
                "definition": "Either of two large ground-dwelling Australian songbirds, of the genus Menura, named because of the beautiful tail feathers of the male of one species, the superb lyrebird (Menura novaehollandiae), which can be erected to look like a lyre, and notable for their extraordinary ability to mimic natural and artificial sounds from their environment.",
                "example": null
              }
            ],
            "part_of_speech": "noun",
            "synonyms": []
          }
        ],
        "phonetics": []
      }
    ],
    "photo": "lyrebird_05122024.jpg",
    "word": "lyrebird"
  },
  {
    "audio": null,
    "categories": [
      "ball_sports_in_general"
    ],
    "level": [
      "C2"
    ],
    "materials": [
      {
        "meanings": [
          {
            "antonyms": [],
            "definitions": [
              {
                "definition": "A player who handles the ball skilfully",
                "example": null
              },
              {
                "definition": "(chiefly in Chicago) A person who specializes in catching home-run and foul balls.",
                "example": null
              }
            ],
            "part_of_speech": "noun",
            "synonyms": []
          }
        ],
        "phonetics": []
      }
    ],
    "photo": null,
    "word": "ballhawk"
  },
  {
    "audio": null,
    "categories": [
      "birds"
    ],
    "level": [
      "C2"
    ],
    "materials": [
      {
        "meanings": [
          {
            "antonyms": [],
            "definitions": [
              {
                "definition": "Any of various long-legged wading birds in the family Threskiornithidae, having long downcurved bills used to probe the mud for prey such as crustaceans.",
                "example": null
              }
            ],
            "part_of_speech": "noun",
            "synonyms": []
          }
        ],
        "phonetics": [
          "/ˈaɪ.bɪs/"
        ]
      }
    ],
    "photo": "ibis_05122024.jpg",
    "word": "ibis"
  },
  {
    "audio": [
      "out of the question_257_05_12_2024.mp3"
    ],
    "categories": [
      "not_allowed"
    ],
    "level": [
      "C1"
    ],
    "materials": [
      {
        "meanings": [
          {
            "antonyms": [],
            "definitions": [
              {
                "definition": "Not remotely possible.",
                "example": null
              }
            ],
            "part_of_speech": "adjective",
            "synonyms": []
          }
        ],
        "phonetics": []
      }
    ],
    "photo": "out of the question_05122024.jpg",
    "word": "out of the question"
  },
  {
    "audio": null,
    "categories": [
      "types_of_crime"
    ],
    "level": [
      "C2"
    ],
    "materials": [
      {
        "meanings": [
          {
            "antonyms": [],
            "definitions": [
              {
                "definition": "Unlawful killing of a human being without malice aforethought, either express or implied, with the absence of intention.",
                "example": null
              }
            ],
            "part_of_speech": "noun",
            "synonyms": []
          }
        ],
        "phonetics": []
      }
    ],
    "photo": null,
    "word": "involuntary manslaughter"
  },
  {
    "audio": [
      "trimester_508_05_12_2024.mp3"
    ],
    "categories": [
      "pregnancy",
      "time_periods"
    ],
    "level": [
      "C2"
    ],
    "materials": [
      {
        "meanings": [
          {
            "antonyms": [],
            "definitions": [
              {
                "definition": "A period of three months or about three months; quarter.",
                "example": "She is in the second trimester of her first pregnancy."
              },
              {
                "definition": "One of the terms of an academic year in those learning institutions that divide their teaching in three roughly equal terms, each about three months long. Compare semester.",
                "example": "The school operates on a trimester schedule."
              }
            ],
            "part_of_speech": "noun",
            "synonyms": []
          }
        ],
        "phonetics": [
          "/tɹaɪˈmɛs.tə(ɹ)/",
          "/tɹaɪˈmɛs.təɹ/"
        ]
      }
    ],
    "photo": "trimester_05122024.jpg",
    "word": "trimester"
  },
  {
    "audio": null,
    "categories": [
      "types_of_illness"
    ],
    "level": [
      "C2"
    ],
    "materials": [
      {
        "meanings": [
          {
            "antonyms": [],
            "definitions": [
              {
                "definition": "Any disorder of the muscles, tendons, joints, bones, nerves, characterized by pain, discomfort and disability.",
                "example": null
              },
              {
                "definition": "Atrophic arthritis, rheumatoid arthritis",
                "example": null
              }
            ],
            "part_of_speech": "noun",
            "synonyms": []
          }
        ],
        "phonetics": [
          "/ˈɹu.məˌtɪz.m̩/"
        ]
      }
    ],
    "photo": "rheumatism_05122024.jpg",
    "word": "rheumatism"
  },
  {
    "audio": null,
    "categories": [
      "describing_weather",
      "tv_and_radio_shows"
    ],
    "level": [
      "B1"
    ],
    "materials": [
      {
        "meanings": [
          {
            "antonyms": [],
            "definitions": [
              {
                "definition": "A prediction of future weather, often for a specific locality, in a newspaper or on the radio or television.",
                "example": "It may be sunny today, but the weather forecast is predicting rain for tomorrow."
              }
            ],
            "part_of_speech": "noun",
            "synonyms": [
              "weather report",
              "weathercast"
            ]
          }
        ],
        "phonetics": []
      }
    ],
    "photo": "weather forecast_05122024.jpg",
    "word": "weather forecast"
  },
  {
    "audio": null,
    "categories": [
      "paying_for_shopping"
    ],
    "level": [
      "C1"
    ],
    "materials": [
      {
        "meanings": [
          {
            "antonyms": [],
            "definitions": [
              {
                "definition": "A card used in a company's loyalty program, which rewards customers who make regular purchases.",
                "example": null
              }
            ],
            "part_of_speech": "noun",
            "synonyms": [
              "courtesy card",
              "fidelity card"
            ]
          }
        ],
        "phonetics": []
      }
    ],
    "photo": "loyalty card_05122024.jpg",
    "word": "loyalty card"
  },
  {
    "audio": [
      "baton_186_05_12_2024.mp3"
    ],
    "categories": [
      "live_music",
      "the_police",
      "athletics"
    ],
    "level": [
      "C2"
    ],
    "materials": [
      {
        "meanings": [
          {
            "antonyms": [],
            "definitions": [
              {
                "definition": "A staff or truncheon, used for various purposes",
                "example": "the baton of a field marshal"
              },
              {
                "definition": "The stick of a conductor in musical performances.",
                "example": null
              },
              {
                "definition": "An object transferred by runners in a relay race.",
                "example": null
              },
              {
                "definition": "A short stout club used primarily by policemen; a truncheon (UK).",
                "example": null
              },
              {
                "definition": "An abatement in coats of arms to denote illegitimacy. (Also spelled batune, baston).",
                "example": null
              },
              {
                "definition": "A riband with the ends cut off, resembling a baton, as shown on a coat of arms.",
                "example": null
              },
              {
                "definition": "A short vertical lightweight post, not set into the ground, used to separate wires in a fence.",
                "example": null
              }
            ],
            "part_of_speech": "noun",
            "synonyms": [
              "billy club",
              "nightstick"
            ]
          },
          {
            "antonyms": [],
            "definitions": [
              {
                "definition": "To strike with a baton.",
                "example": null
              }
            ],
            "part_of_speech": "verb",
            "synonyms": []
          }
        ],
        "phonetics": [
          "/ˈbætɒn/",
          "/bəˈtɑn/"
        ]
      }
    ],
    "photo": "baton_05122024.jpg",
    "word": "baton"
  },
  {
    "audio": [
      "biblical_926_05_12_2024.mp3"
    ],
    "categories": [
      "religious_texts"
    ],
    "level": [
      "C2"
    ],
    "materials": [
      {
        "meanings": [
          {
            "antonyms": [
              "unbiblical"
            ],
            "definitions": [
              {
                "definition": "Of or relating to the Bible.",
                "example": "Tithing is both a quranic and biblical virtue."
              },
              {
                "definition": "In accordance with the teachings of the Bible (according to some interpretation of it).",
                "example": "The biblical teaching is that [...]"
              },
              {
                "definition": "Very great; especially, exceeding previous records in scale.",
                "example": "of biblical proportions; with biblical fury"
              }
            ],
            "part_of_speech": "adjective",
            "synonyms": []
          }
        ],
        "phonetics": [
          "/ˈbɪblɪkəl/"
        ]
      }
    ],
    "photo": "biblical_05122024.jpg",
    "word": "biblical"
  },
  {
    "audio": null,
    "categories": [
      "showing_interest"
    ],
    "level": [
      "C1"
    ],
    "materials": [
      {
        "meanings": [
          {
            "antonyms": [],
            "definitions": [
              {
                "definition": "The act of bewitching, or enchanting",
                "example": null
              },
              {
                "definition": "The state or condition of being fascinated.",
                "example": "To my fascination, the skies turned all kinds of colours."
              },
              {
                "definition": "Something which fascinates.",
                "example": "Life after death had always been a great fascination to him."
              }
            ],
            "part_of_speech": "noun",
            "synonyms": [
              "enchantment",
              "witchcraft"
            ]
          }
        ],
        "phonetics": [
          "/fæsɪˈneɪʃən/"
        ]
      }
    ],
    "photo": "fascination_05122024.jpg",
    "word": "fascination"
  },
  {
    "audio": null,
    "categories": [
      "the_police",
      "political_views_and_systems"
    ],
    "level": [
      "C1"
    ],
    "materials": [
      {
        "meanings": [
          {
            "antonyms": [],
            "definitions": [
              {
                "definition": "(usually derogatory) An enforcement institution designed to protect an autocratic government via strict and repressive control of the people.",
                "example": null
              }
            ],
            "part_of_speech": "noun",
            "synonyms": []
          }
        ],
        "phonetics": []
      }
    ],
    "photo": "police state_05122024.jpg",
    "word": "police state"
  },
  {
    "audio": null,
    "categories": [
      "pregnancy"
    ],
    "level": [
      "C2"
    ],
    "materials": [
      {
        "meanings": [
          {
            "antonyms": [],
            "definitions": [
              {
                "definition": "A person who is expecting to give birth.",
                "example": null
              },
              {
                "definition": "A dietary supplement to be taken by somebody expecting to give birth.",
                "example": "She was recommended a course of zinc prenatals."
              }
            ],
            "part_of_speech": "noun",
            "synonyms": []
          },
          {
            "antonyms": [],
            "definitions": [
              {
                "definition": "Being or happening before birth.",
                "example": null
              }
            ],
            "part_of_speech": "adjective",
            "synonyms": [
              "antenatal"
            ]
          }
        ],
        "phonetics": []
      }
    ],
    "photo": "prenatal_05122024.jpg",
    "word": "prenatal"
  },
  {
    "audio": null,
    "categories": [
      "types_of_illness"
    ],
    "level": [
      "C2"
    ],
    "materials": [
      {
        "meanings": [
          {
            "antonyms": [],
            "definitions": [
              {
                "definition": "Inflammation of the tonsils.",
                "example": null
              }
            ],
            "part_of_speech": "noun",
            "synonyms": []
          }
        ],
        "phonetics": [
          "/tɒnsəˈlaɪtɪs/"
        ]
      }
    ],
    "photo": "tonsillitis_05122024.jpg",
    "word": "tonsillitis"
  },
  {
    "audio": null,
    "categories": [
      "broadcasting",
      "in_the_theatre"
    ],
    "level": [
      "C2"
    ],
    "materials": [
      {
        "meanings": [
          {
            "antonyms": [],
            "definitions": [
              {
                "definition": "In a television studio, theatre or concert hall, the room where performers await their entrance.",
                "example": null
              },
              {
                "definition": "The inside of a tube (i.e. of a wave making a tube).",
                "example": null
              }
            ],
            "part_of_speech": "noun",
            "synonyms": [
              "tiring-house",
              "tiring-room"
            ]
          }
        ],
        "phonetics": []
      }
    ],
    "photo": "green room_05122024.jpg",
    "word": "green room"
  },
  {
    "audio": null,
    "categories": [
      "birds"
    ],
    "level": [
      "C2"
    ],
    "materials": [
      {
        "meanings": [
          {
            "antonyms": [],
            "definitions": [
              {
                "definition": "Any of the birds, such as ducks, geese and swans, that spend most of their non-flying time on water; especially those of the family Anatidae.",
                "example": null
              }
            ],
            "part_of_speech": "noun",
            "synonyms": [
              "wildfowl"
            ]
          }
        ],
        "phonetics": []
      }
    ],
    "photo": "waterfowl_05122024.jpg",
    "word": "waterfowl"
  },
  {
    "audio": [
      "reservoir_899_05_12_2024.mp3"
    ],
    "categories": [
      "rivers_and_lakes"
    ],
    "level": [
      "C1"
    ],
    "materials": [
      {
        "meanings": [
          {
            "antonyms": [],
            "definitions": [
              {
                "definition": "A place where anything is kept in store",
                "example": null
              },
              {
                "definition": "A large natural or artificial lake used as a source of water supply.",
                "example": null
              },
              {
                "definition": "A small intercellular space, often containing resin, essential oil, or some other secreted matter.",
                "example": null
              },
              {
                "definition": "A supply or source of something.",
                "example": null
              },
              {
                "definition": "A species that acts as host to a zoonosis when it is not causing acute illness in other susceptible species.",
                "example": null
              }
            ],
            "part_of_speech": "noun",
            "synonyms": []
          }
        ],
        "phonetics": [
          "/ˈɹɛz.ə(ɹ).vwɑɹ/",
          "/ˈɹɛz.ə.vwɑː(ɹ)/"
        ]
      }
    ],
    "photo": "reservoir_05122024.jpg",
    "word": "reservoir"
  },
  {
    "audio": [
      "gramme_501_05_12_2024.mp3"
    ],
    "categories": [
      "measurements",
      "preparing_food"
    ],
    "level": [
      "B2"
    ],
    "materials": [
      {
        "meanings": [
          {
            "antonyms": [],
            "definitions": [
              {
                "definition": "Gram (unit of mass)",
                "example": null
              }
            ],
            "part_of_speech": "noun",
            "synonyms": []
          }
        ],
        "phonetics": [
          "/ɡɹæm/"
        ]
      }
    ],
    "photo": "gramme_05122024.jpg",
    "word": "gramme"
  },
  {
    "audio": [
      "maple_311_05_12_2024.mp3"
    ],
    "categories": [
      "trees"
    ],
    "level": [
      "C1"
    ],
    "materials": [
      {
        "meanings": [
          {
            "antonyms": [],
            "definitions": [
              {
                "definition": "A tree of the Acer genus, characterised by its usually palmate leaves and winged seeds.",
                "example": null
              },
              {
                "definition": "The wood of such a tree, prized for its hardness and attractive appearance",
                "example": null
              }
            ],
            "part_of_speech": "noun",
            "synonyms": []
          }
        ],
        "phonetics": [
          "/ˈmeɪpl̩/"
        ]
      }
    ],
    "photo": "maple_05122024.jpg",
    "word": "maple"
  },
  {
    "audio": null,
    "categories": [
      "love"
    ],
    "level": [
      "C2"
    ],
    "materials": [
      {
        "meanings": [
          {
            "antonyms": [
              "underprotective"
            ],
            "definitions": [
              {
                "definition": "Excessively protective, wanting to give too much protection (especially to children)",
                "example": null
              }
            ],
            "part_of_speech": "adjective",
            "synonyms": []
          }
        ],
        "phonetics": [
          "/ˌoʊvɚpɹəˈtɛktɪv/",
          "/ˌəʊvəpɹəˈtɛktɪv/"
        ]
      }
    ],
    "photo": "overprotective_05122024.jpg",
    "word": "overprotective"
  },
  {
    "audio": null,
    "categories": [
      "live_music",
      "machines_and_devices"
    ],
    "level": [
      "C1"
    ],
    "materials": [
      {
        "meanings": [
          {
            "antonyms": [],
            "definitions": [
              {
                "definition": "Anything that amplifies, or makes something larger or more intense.",
                "example": null
              },
              {
                "definition": "An adverb that adds intensity, such as \"really\" or \"totally\".",
                "example": null
              },
              {
                "definition": "An appliance or circuit that increases the strength of a weak electrical signal without changing the other characteristics of the signal.",
                "example": null
              },
              {
                "definition": "A portable encasement that houses a large speaker, used to amplify voices and musical instruments at live performances.",
                "example": null
              },
              {
                "definition": "A lens that enlarges the field of vision.",
                "example": null
              }
            ],
            "part_of_speech": "noun",
            "synonyms": []
          }
        ],
        "phonetics": [
          "/ˈæm.plə.faɪ.ə/",
          "/ˈæm.plə.faɪ.əɹ/"
        ]
      }
    ],
    "photo": "amplifier_05122024.jpg",
    "word": "amplifier"
  },
  {
    "audio": null,
    "categories": [
      "styles_of_music"
    ],
    "level": [
      "C2"
    ],
    "materials": [
      {
        "meanings": [
          {
            "antonyms": [],
            "definitions": [
              {
                "definition": "A genre of rock music, normally published on independent labels, comprising many subgenres, most distinguished by the prevalence of thick and distorted guitar music.",
                "example": null
              }
            ],
            "part_of_speech": "noun",
            "synonyms": []
          }
        ],
        "phonetics": []
      }
    ],
    "photo": "alternative rock_05122024.jpg",
    "word": "alternative rock"
  },
  {
    "audio": null,
    "categories": [
      "mathematical_terminology"
    ],
    "level": [
      "C2"
    ],
    "materials": [
      {
        "meanings": [
          {
            "antonyms": [],
            "definitions": [
              {
                "definition": "In a right triangle, the ratio of the length of the side opposite an angle to the length of the hypotenuse.",
                "example": null
              }
            ],
            "part_of_speech": "noun",
            "synonyms": [
              "sin"
            ]
          }
        ],
        "phonetics": [
          "/saɪn/"
        ]
      }
    ],
    "photo": "sine_05122024.jpg",
    "word": "sine"
  },
  {
    "audio": null,
    "categories": [
      "months"
    ],
    "level": [
      "C2"
    ],
    "materials": [
      {
        "meanings": [
          {
            "antonyms": [],
            "definitions": [
              {
                "definition": "The period of duration from the first date of one month to the last date of the same month, which can thus vary from 28 to 31 days in length.",
                "example": null
              }
            ],
            "part_of_speech": "noun",
            "synonyms": []
          }
        ],
        "phonetics": []
      }
    ],
    "photo": "calendar month_05122024.jpg",
    "word": "calendar month"
  },
  {
    "audio": [
      "dial_051_05_12_2024.mp3"
    ],
    "categories": [
      "making_calls",
      "how_machines_work",
      "parts_of_a_car"
    ],
    "level": [
      "C1"
    ],
    "materials": [
      {
        "meanings": [
          {
            "antonyms": [],
            "definitions": [
              {
                "definition": "A graduated, circular scale over which a needle moves to show a measurement (such as speed).",
                "example": null
              },
              {
                "definition": "A clock face.",
                "example": null
              },
              {
                "definition": "A sundial.",
                "example": null
              },
              {
                "definition": "A panel on a radio etc showing wavelengths or channels; a knob that is turned to change the wavelength etc.",
                "example": null
              },
              {
                "definition": "A disk with finger holes on a telephone; used to select the number to be called.",
                "example": null
              },
              {
                "definition": "A person's face.",
                "example": null
              },
              {
                "definition": "A miner's compass.",
                "example": null
              }
            ],
            "part_of_speech": "noun",
            "synonyms": []
          },
          {
            "antonyms": [],
            "definitions": [
              {
                "definition": "To control or select something with a dial, or (figuratively) as if with a dial.",
                "example": "President Trump has recently dialled down the rhetoric."
              },
              {
                "definition": "To select a number, or to call someone, on a telephone.",
                "example": "In an emergency dial 999."
              },
              {
                "definition": "To use a dial or a telephone.",
                "example": "Please be careful when dialling."
              }
            ],
            "part_of_speech": "verb",
            "synonyms": []
          }
        ],
        "phonetics": [
          "/ˈdaɪəɫ/"
        ]
      }
    ],
    "photo": "dial_05122024.jpg",
    "word": "dial"
  },
  {
    "audio": null,
    "categories": [
      "old_age"
    ],
    "level": [
      "C2"
    ],
    "materials": [
      {
        "meanings": [
          {
            "antonyms": [],
            "definitions": [
              {
                "definition": "The state or period of being a widow or widower.",
                "example": null
              }
            ],
            "part_of_speech": "noun",
            "synonyms": []
          }
        ],
        "phonetics": []
      }
    ],
    "photo": "widowhood_05122024.jpg",
    "word": "widowhood"
  },
  {
    "audio": null,
    "categories": [
      "birds"
    ],
    "level": [
      "C1"
    ],
    "materials": [
      {
        "meanings": [
          {
            "antonyms": [],
            "definitions": [
              {
                "definition": "A carnivorous bird that hunts for its food, especially one that preys on vertebrates.",
                "example": null
              }
            ],
            "part_of_speech": "noun",
            "synonyms": [
              "raptor"
            ]
          }
        ],
        "phonetics": []
      }
    ],
    "photo": "bird of prey_05122024.jpg",
    "word": "bird of prey"
  },
  {
    "audio": null,
    "categories": [
      "airports"
    ],
    "level": [
      "C2"
    ],
    "materials": [
      {
        "meanings": [
          {
            "antonyms": [],
            "definitions": [
              {
                "definition": "A moving walkway; a slow conveyor belt that transports people horizontally or on an incline in a similar manner to an escalator.",
                "example": null
              }
            ],
            "part_of_speech": "noun",
            "synonyms": [
              "moving walkway"
            ]
          }
        ],
        "phonetics": []
      }
    ],
    "photo": "travelator_05122024.jpg",
    "word": "travelator"
  },
  {
    "audio": null,
    "categories": [
      "the_economy"
    ],
    "level": [
      "B2"
    ],
    "materials": [
      {
        "meanings": [
          {
            "antonyms": [],
            "definitions": [
              {
                "definition": "Any money owed by the government of a nation.",
                "example": null
              }
            ],
            "part_of_speech": "noun",
            "synonyms": []
          }
        ],
        "phonetics": []
      }
    ],
    "photo": "national debt_05122024.jpg",
    "word": "national debt"
  },
  {
    "audio": null,
    "categories": [
      "types_of_crime"
    ],
    "level": [
      "C1"
    ],
    "materials": [
      {
        "meanings": [
          {
            "antonyms": [],
            "definitions": [
              {
                "definition": "A large criminal organization, or a group of such organizations, that deals in illegal goods and services.",
                "example": "Organized crime is largely responsible for the nation’s illicit drug trafficking."
              },
              {
                "definition": "The crimes perpetrated by those organizations.",
                "example": "Organized crime has dramatically increased in our neighbourhood."
              }
            ],
            "part_of_speech": "noun",
            "synonyms": []
          }
        ],
        "phonetics": []
      }
    ],
    "photo": "organized crime_05122024.jpg",
    "word": "organized crime"
  },
  {
    "audio": null,
    "categories": [
      "annoying",
      "anger"
    ],
    "level": [
      "C2"
    ],
    "materials": [
      {
        "meanings": [
          {
            "antonyms": [],
            "definitions": [
              {
                "definition": "A low two-wheeled cart, used in harness racing.",
                "example": null
              },
              {
                "definition": "Any carriage seating only the driver.",
                "example": null
              }
            ],
            "part_of_speech": "noun",
            "synonyms": []
          },
          {
            "antonyms": [],
            "definitions": [
              {
                "definition": "Silent and withdrawn after being upset",
                "example": "the sulky child"
              }
            ],
            "part_of_speech": "adjective",
            "synonyms": [
              "morose",
              "sullen"
            ]
          }
        ],
        "phonetics": []
      }
    ],
    "photo": "sulky_05122024.jpg",
    "word": "sulky"
  },
  {
    "audio": null,
    "categories": [
      "unhappiness"
    ],
    "level": [
      "C1"
    ],
    "materials": [
      {
        "meanings": [
          {
            "antonyms": [],
            "definitions": [
              {
                "definition": "Suffering from grief, especially after a failed romance.",
                "example": "When he told me he didn't want to see me anymore, I was heartbroken."
              }
            ],
            "part_of_speech": "adjective",
            "synonyms": [
              "brokenhearted",
              "dejected",
              "despairing",
              "devastated",
              "disconsolate",
              "discouraged",
              "distraught",
              "forlorn",
              "grief-stricken",
              "inconsolable",
              "wretched"
            ]
          }
        ],
        "phonetics": []
      }
    ],
    "photo": "heartbroken_05122024.jpg",
    "word": "heartbroken"
  },
  {
    "audio": null,
    "categories": [
      "broadcasting"
    ],
    "level": [
      "C1"
    ],
    "materials": [
      {
        "meanings": [
          {
            "antonyms": [],
            "definitions": [
              {
                "definition": "The office of a news organisation, especially that part of it where the journalists work and news stories are processed.",
                "example": null
              },
              {
                "definition": "A room where newspapers and magazines are available for reading.",
                "example": null
              }
            ],
            "part_of_speech": "noun",
            "synonyms": []
          }
        ],
        "phonetics": [
          "/ˈnjuːzɹuːm/"
        ]
      }
    ],
    "photo": "newsroom_05122024.jpg",
    "word": "newsroom"
  },
  {
    "audio": [
      "diode_654_05_12_2024.mp3"
    ],
    "categories": [
      "electronics"
    ],
    "level": [
      "C2"
    ],
    "materials": [
      {
        "meanings": [
          {
            "antonyms": [],
            "definitions": [
              {
                "definition": "An electronic device that allows current to flow in one direction only; used chiefly as a rectifier.",
                "example": null
              }
            ],
            "part_of_speech": "noun",
            "synonyms": []
          }
        ],
        "phonetics": [
          "/ˈdaɪəʊd/",
          "/ˈdaɪoʊd/"
        ]
      }
    ],
    "photo": "diode_05122024.jpg",
    "word": "diode"
  },
  {
    "audio": [
      "nettle_039_05_12_2024.mp3"
    ],
    "categories": [
      "anger",
      "plants"
    ],
    "level": [
      "C2"
    ],
    "materials": [
      {
        "meanings": [
          {
            "antonyms": [],
            "definitions": [
              {
                "definition": "Any plant whose foliage is covered with stinging, mildly poisonous hairs, causing an instant rash.",
                "example": null
              },
              {
                "definition": "Certain plants that have spines or prickles:",
                "example": null
              },
              {
                "definition": "Certain non-stinging plants, mostly in the family Lamiaceae, that resemble the species of Urtica:",
                "example": null
              },
              {
                "definition": "Loosely, anything which causes a similarly stinging rash, such as a jellyfish or sea nettle.",
                "example": null
              }
            ],
            "part_of_speech": "noun",
            "synonyms": []
          },
          {
            "antonyms": [],
            "definitions": [
              {
                "definition": "Of the nettle plant and similar physical causes, to sting, causing a rash in someone.",
                "example": "The children were badly nettled after playing in the field."
              },
              {
                "definition": "To pique, irritate, vex or provoke.",
                "example": null
              }
            ],
            "part_of_speech": "verb",
            "synonyms": []
          }
        ],
        "phonetics": [
          "/ˈnɛt(ə)l/"
        ]
      }
    ],
    "photo": "nettle_05122024.jpg",
    "word": "nettle"
  },
  {
    "audio": null,
    "categories": [
      "train_and_bus_travel"
    ],
    "level": [
      "C1"
    ],
    "materials": [
      {
        "meanings": [
          {
            "antonyms": [],
            "definitions": [
              {
                "definition": "A commuter rail system that combines aspects of an interurban railway with those of a subway, using a menagerie of pathways such as viaduct, tunnel, beam, cut and cover, trench, at grade, and others.",
                "example": null
              }
            ],
            "part_of_speech": "noun",
            "synonyms": []
          }
        ],
        "phonetics": []
      }
    ],
    "photo": "rapid transit_05122024.jpg",
    "word": "rapid transit"
  },
  {
    "audio": [
      "greenwash_077_05_12_2024.mp3"
    ],
    "categories": [
      "conservation"
    ],
    "level": [
      "C2"
    ],
    "materials": [
      {
        "meanings": [
          {
            "antonyms": [],
            "definitions": [
              {
                "definition": "A false or misleading picture of environmental friendliness used to conceal or obscure damaging activities.",
                "example": null
              }
            ],
            "part_of_speech": "noun",
            "synonyms": []
          },
          {
            "antonyms": [],
            "definitions": [
              {
                "definition": "To disseminate such information about (something).",
                "example": null
              }
            ],
            "part_of_speech": "verb",
            "synonyms": []
          }
        ],
        "phonetics": [
          "/ˈɡɹiːnwɒʃ/"
        ]
      }
    ],
    "photo": null,
    "word": "greenwash"
  },
  {
    "audio": null,
    "categories": [
      "the_press"
    ],
    "level": [
      "C2"
    ],
    "materials": [
      {
        "meanings": [
          {
            "antonyms": [],
            "definitions": [
              {
                "definition": "A tabloid newspaper containing gossip and sensational news stories pertaining especially to well-known people.",
                "example": null
              }
            ],
            "part_of_speech": "noun",
            "synonyms": []
          }
        ],
        "phonetics": []
      }
    ],
    "photo": "scandal sheet_05122024.jpg",
    "word": "scandal sheet"
  },
  {
    "audio": null,
    "categories": [
      "embarrassment"
    ],
    "level": [
      "C1"
    ],
    "materials": [
      {
        "meanings": [
          {
            "antonyms": [
              "dignify",
              "honor"
            ],
            "definitions": [
              {
                "definition": "To injure the dignity and self-respect of.",
                "example": null
              },
              {
                "definition": "To make humble; to lower in condition or status.",
                "example": null
              }
            ],
            "part_of_speech": "verb",
            "synonyms": [
              "debase",
              "demean",
              "disgrace",
              "humble",
              "mortify",
              "shame"
            ]
          }
        ],
        "phonetics": [
          "/hjuːˈmɪliˌeɪt/"
        ]
      }
    ],
    "photo": "humiliate_05122024.jpg",
    "word": "humiliate"
  },
  {
    "audio": null,
    "categories": [
      "race"
    ],
    "level": [
      "C2"
    ],
    "materials": [
      {
        "meanings": [
          {
            "antonyms": [],
            "definitions": [
              {
                "definition": "A group of vigilantes intent on lynching someone.",
                "example": null
              }
            ],
            "part_of_speech": "noun",
            "synonyms": []
          }
        ],
        "phonetics": []
      }
    ],
    "photo": "lynch mob_05122024.jpg",
    "word": "lynch mob"
  },
  {
    "audio": [
      "links_834_05_12_2024.mp3"
    ],
    "categories": [
      "golf"
    ],
    "level": [
      "C2"
    ],
    "materials": [
      {
        "meanings": [
          {
            "antonyms": [],
            "definitions": [
              {
                "definition": "Some text or a graphic in an electronic document that can be activated to display another document or trigger an action.",
                "example": "Click the hyperlink to go to the next page."
              },
              {
                "definition": "(by extension) An address, URL, or program that defines a hyperlink's function.",
                "example": "Copy the hyperlink and paste it into an email."
              }
            ],
            "part_of_speech": "noun",
            "synonyms": [
              "link"
            ]
          },
          {
            "antonyms": [],
            "definitions": [
              {
                "definition": "A connection between places, people, events, things, or ideas.",
                "example": "The mayor’s assistant serves as the link to the media."
              },
              {
                "definition": "One element of a chain or other connected series.",
                "example": "The third link of the silver chain needs to be resoldered."
              },
              {
                "definition": "The connection between buses or systems.",
                "example": "A by-N-link is composed of N lanes."
              },
              {
                "definition": "A space comprising one or more disjoint knots.",
                "example": null
              },
              {
                "definition": "A thin wild bank of land splitting two cultivated patches and often linking two hills.",
                "example": null
              },
              {
                "definition": "An individual person or element in a system",
                "example": null
              },
              {
                "definition": "Anything doubled and closed like a link of a chain.",
                "example": "a link of horsehair"
              },
              {
                "definition": "A sausage that is not a patty.",
                "example": null
              },
              {
                "definition": "(kinematics) Any one of the several elementary pieces of a mechanism, such as the fixed frame, or a rod, wheel, mass of confined liquid, etc., by which relative motion of other parts is produced and constrained.",
                "example": null
              },
              {
                "definition": "Any intermediate rod or piece for transmitting force or motion, especially a short connecting rod with a bearing at each end; specifically (in steam engines) the slotted bar, or connecting piece, to the opposite ends of which the eccentric rods are jointed, and by means of which the movement of the valve is varied, in a link motion.",
                "example": null
              },
              {
                "definition": "The length of one joint of Gunter's chain, being the hundredth part of it, or 7.92 inches, the chain being 66 feet in length.",
                "example": null
              },
              {
                "definition": "A bond of affinity, or a unit of valence between atoms; applied to a unit of chemical force or attraction.",
                "example": null
              },
              {
                "definition": "(plural) The windings of a river; the land along a winding stream.",
                "example": null
              }
            ],
            "part_of_speech": "noun",
            "synonyms": [
              "connection"
            ]
          },
          {
            "antonyms": [],
            "definitions": [
              {
                "definition": "To connect two or more things.",
                "example": null
              },
              {
                "definition": "(of a Web page) To contain a hyperlink to another page.",
                "example": "My homepage links to my wife's."
              },
              {
                "definition": "To supply (somebody) with a hyperlink; to direct by means of a link.",
                "example": "Haven't you seen his Web site? I'll link you to it."
              },
              {
                "definition": "To post a hyperlink to.",
                "example": "Stop linking those unfunny comics all the time!"
              },
              {
                "definition": "To demonstrate a correlation between two things.",
                "example": null
              },
              {
                "definition": "To combine objects generated by a compiler into a single executable.",
                "example": null
              }
            ],
            "part_of_speech": "verb",
            "synonyms": [
              "affix",
              "attach",
              "join",
              "put together"
            ]
          },
          {
            "antonyms": [],
            "definitions": [
              {
                "definition": "A torch, used to light dark streets.",
                "example": null
              }
            ],
            "part_of_speech": "noun",
            "synonyms": []
          },
          {
            "antonyms": [],
            "definitions": [
              {
                "definition": "To skip or trip along smartly; to go quickly.",
                "example": null
              }
            ],
            "part_of_speech": "verb",
            "synonyms": []
          }
        ],
        "phonetics": [
          "/lɪŋks/"
        ]
      },
      {
        "meanings": [
          {
            "antonyms": [],
            "definitions": [
              {
                "definition": "A golf course, especially one situated on dunes by the sea.",
                "example": null
              }
            ],
            "part_of_speech": "noun",
            "synonyms": []
          }
        ],
        "phonetics": [
          "/lɪŋks/"
        ]
      }
    ],
    "photo": "links_05122024.jpg",
    "word": "links"
  },
  {
    "audio": [
      "dinghy_959_05_12_2024.mp3"
    ],
    "categories": [
      "types_of_boat"
    ],
    "level": [
      "C2"
    ],
    "materials": [
      {
        "meanings": [
          {
            "antonyms": [],
            "definitions": [
              {
                "definition": "A small open boat, propelled by oars or paddles, carried as a tender, lifeboat, or pleasure craft on a ship.",
                "example": null
              },
              {
                "definition": "An inflatable rubber life raft.",
                "example": null
              }
            ],
            "part_of_speech": "noun",
            "synonyms": [
              "tender"
            ]
          },
          {
            "antonyms": [],
            "definitions": [
              {
                "definition": "To travel by dinghy.",
                "example": null
              }
            ],
            "part_of_speech": "verb",
            "synonyms": []
          }
        ],
        "phonetics": [
          "/ˈdɪŋ(ɡ)i/",
          "/ˈdɪŋ.i/"
        ]
      }
    ],
    "photo": "dinghy_05122024.jpg",
    "word": "dinghy"
  },
  {
    "audio": null,
    "categories": [
      "time_expressions"
    ],
    "level": [
      "C2"
    ],
    "materials": [
      {
        "meanings": [
          {
            "antonyms": [],
            "definitions": [
              {
                "definition": "In front of.",
                "example": "A hill loomed ahead of them."
              },
              {
                "definition": "Preceding.",
                "example": "He's giving a series of concerts in London ahead of his international tour."
              },
              {
                "definition": "In the future of.",
                "example": "Peter has a lot of work ahead of him."
              },
              {
                "definition": "In advance of.",
                "example": "I arrived at the suite half an hour ahead of Jack."
              },
              {
                "definition": "Having made more progress than.",
                "example": "He is far ahead of his class in math."
              }
            ],
            "part_of_speech": "preposition",
            "synonyms": []
          }
        ],
        "phonetics": []
      }
    ],
    "photo": "ahead of_05122024.jpg",
    "word": "ahead of"
  },
  {
    "audio": null,
    "categories": [
      "running_a_business"
    ],
    "level": [
      "C2"
    ],
    "materials": [
      {
        "meanings": [
          {
            "antonyms": [],
            "definitions": [
              {
                "definition": "To do, carry through, conduct or perform some action.",
                "example": null
              },
              {
                "definition": "To carry over, hand over or transfer something.",
                "example": null
              },
              {
                "definition": "To conduct business.",
                "example": null
              },
              {
                "definition": "To exchange or trade, as of ideas, money, goods, etc.",
                "example": null
              }
            ],
            "part_of_speech": "verb",
            "synonyms": []
          }
        ],
        "phonetics": []
      }
    ],
    "photo": "transact_05122024.jpg",
    "word": "transact"
  },
  {
    "audio": null,
    "categories": [
      "the_economy"
    ],
    "level": [
      "C2"
    ],
    "materials": [
      {
        "meanings": [
          {
            "antonyms": [],
            "definitions": [
              {
                "definition": "A jurisdiction that levies low tax rates on certain economic activities, especially to attract wealthy individuals and (foreign) businesses.",
                "example": null
              }
            ],
            "part_of_speech": "noun",
            "synonyms": []
          }
        ],
        "phonetics": []
      }
    ],
    "photo": "tax haven_05122024.jpg",
    "word": "tax haven"
  },
  {
    "audio": [
      "flatline_264_05_12_2024.mp3"
    ],
    "categories": [
      "resulting_in_failure"
    ],
    "level": [
      "C2"
    ],
    "materials": [
      {
        "meanings": [
          {
            "antonyms": [],
            "definitions": [
              {
                "definition": "An unchanging state, as indicated in a graph of a variable over time.",
                "example": null
              },
              {
                "definition": "Asystole; the absence of heart contractions or brain waves.",
                "example": null
              }
            ],
            "part_of_speech": "noun",
            "synonyms": []
          },
          {
            "antonyms": [],
            "definitions": [
              {
                "definition": "(of the heart) To stop beating.",
                "example": null
              },
              {
                "definition": "(by extension) To die.",
                "example": null
              },
              {
                "definition": "To kill.",
                "example": null
              },
              {
                "definition": "To stay at the same level, without development; or, to fall.",
                "example": null
              }
            ],
            "part_of_speech": "verb",
            "synonyms": []
          }
        ],
        "phonetics": [
          "/ˈflætˌlaɪn/"
        ]
      }
    ],
    "photo": null,
    "word": "flatline"
  },
  {
    "audio": null,
    "categories": [
      "using_the_internet"
    ],
    "level": [
      "C2"
    ],
    "materials": [
      {
        "meanings": [
          {
            "antonyms": [],
            "definitions": [
              {
                "definition": "Any species known only from trace fossils, such as footprints, coprolites or nests.",
                "example": null
              }
            ],
            "part_of_speech": "noun",
            "synonyms": []
          }
        ],
        "phonetics": []
      }
    ],
    "photo": "ISP_05122024.jpg",
    "word": "ISP"
  },
  {
    "audio": null,
    "categories": [
      "bird_behaviour"
    ],
    "level": [
      "C2"
    ],
    "materials": [
      {
        "meanings": [
          {
            "antonyms": [],
            "definitions": [
              {
                "definition": "A short, sharp or high note or noise, as of a bird or insect.",
                "example": null
              },
              {
                "definition": "(radar, sonar, radio telescopy etc.) A pulse of signal whose frequency sweeps through a band of frequencies for the duration of the pulse.",
                "example": null
              }
            ],
            "part_of_speech": "noun",
            "synonyms": []
          },
          {
            "antonyms": [],
            "definitions": [
              {
                "definition": "To make a short, sharp, cheerful note, as of small birds or crickets",
                "example": null
              },
              {
                "definition": "To speak in a high-pitched staccato",
                "example": null
              },
              {
                "definition": "(radar, sonar, radio telescopy etc.) To modify (a pulse of signal) so that it sweeps through a band of frequencies throughout its duration.",
                "example": null
              },
              {
                "definition": "To cheer up; to make (someone) happier.",
                "example": null
              }
            ],
            "part_of_speech": "verb",
            "synonyms": []
          }
        ],
        "phonetics": [
          "/tʃɜː(ɹ)p/"
        ]
      }
    ],
    "photo": "chirp_05122024.jpg",
    "word": "chirp"
  },
  {
    "audio": null,
    "categories": [
      "types_of_crime"
    ],
    "level": [
      "C2"
    ],
    "materials": [
      {
        "meanings": [
          {
            "antonyms": [],
            "definitions": [
              {
                "definition": "To approach slowly and quietly in order not to be discovered when getting closer.",
                "example": null
              },
              {
                "definition": "To (try to) follow or contact someone constantly, often resulting in harassment.Wp",
                "example": "My ex-girlfriend is stalking me."
              },
              {
                "definition": "To walk slowly and cautiously; to walk in a stealthy, noiseless manner.",
                "example": null
              },
              {
                "definition": "To walk behind something, such as a screen, for the purpose of approaching game; to proceed under cover.",
                "example": null
              }
            ],
            "part_of_speech": "verb",
            "synonyms": []
          },
          {
            "antonyms": [],
            "definitions": [
              {
                "definition": "To walk haughtily.",
                "example": null
              }
            ],
            "part_of_speech": "verb",
            "synonyms": []
          }
        ],
        "phonetics": []
      },
      {
        "meanings": [
          {
            "antonyms": [],
            "definitions": [
              {
                "definition": "The act of going stealthily.",
                "example": null
              },
              {
                "definition": "Hunting for game by moving silently and stealthily or by waiting in ambush.",
                "example": null
              },
              {
                "definition": "The crime of following or harassing another person, causing him or her to fear death or injury.",
                "example": null
              }
            ],
            "part_of_speech": "noun",
            "synonyms": []
          }
        ],
        "phonetics": []
      },
      {
        "meanings": [
          {
            "antonyms": [],
            "definitions": [
              {
                "definition": "The removal of stalks from bunches of grapes prior to winemaking.",
                "example": null
              }
            ],
            "part_of_speech": "noun",
            "synonyms": []
          }
        ],
        "phonetics": []
      }
    ],
    "photo": "stalking_05122024.jpg",
    "word": "stalking"
  },
  {
    "audio": [
      "capillary_898_05_12_2024.mp3"
    ],
    "categories": [
      "inside_the_body"
    ],
    "level": [
      "C2"
    ],
    "materials": [
      {
        "meanings": [
          {
            "antonyms": [],
            "definitions": [
              {
                "definition": "A narrow tube.",
                "example": null
              },
              {
                "definition": "Any of the small blood vessels that connect arteries to veins.",
                "example": null
              }
            ],
            "part_of_speech": "noun",
            "synonyms": []
          },
          {
            "antonyms": [],
            "definitions": [
              {
                "definition": "Of or pertaining to hair.",
                "example": null
              },
              {
                "definition": "Pertaining to a narrow tube.",
                "example": null
              },
              {
                "definition": "Of, relating to, or caused by surface tension.",
                "example": null
              }
            ],
            "part_of_speech": "adjective",
            "synonyms": []
          }
        ],
        "phonetics": [
          "/ˈkæpɪˌlɛɹi/",
          "/kəˈpɪ.lə.ɹi/"
        ]
      }
    ],
    "photo": "capillary_05122024.jpg",
    "word": "capillary"
  },
  {
    "audio": [
      "fielder_031_05_12_2024.mp3"
    ],
    "categories": [
      "cricket"
    ],
    "level": [
      "C2"
    ],
    "materials": [
      {
        "meanings": [
          {
            "antonyms": [],
            "definitions": [
              {
                "definition": "A player of the fielding side, whose task is to gather the ball after the batsman has hit it, to catch the batsman out, or to prevent him from scoring.",
                "example": null
              },
              {
                "definition": "A defensive player in the field.",
                "example": null
              },
              {
                "definition": "A dog trained in pursuit of game in the field.",
                "example": null
              },
              {
                "definition": "One who fields anything.",
                "example": null
              }
            ],
            "part_of_speech": "noun",
            "synonyms": []
          }
        ],
        "phonetics": []
      }
    ],
    "photo": "fielder_05122024.jpg",
    "word": "fielder"
  },
  {
    "audio": null,
    "categories": [
      "pieces_of_music"
    ],
    "level": [
      "C2"
    ],
    "materials": [
      {
        "meanings": [
          {
            "antonyms": [],
            "definitions": [
              {
                "definition": "A 16th century Spanish dance; the zarabanda",
                "example": null
              },
              {
                "definition": "A stately Baroque dance in slow triple time",
                "example": null
              },
              {
                "definition": "The music for either dance of the same name.",
                "example": null
              }
            ],
            "part_of_speech": "noun",
            "synonyms": []
          }
        ],
        "phonetics": []
      }
    ],
    "photo": null,
    "word": "saraband"
  },
  {
    "audio": null,
    "categories": [
      "meat_fish_and_seafood"
    ],
    "level": [
      "C2"
    ],
    "materials": [
      {
        "meanings": [
          {
            "antonyms": [],
            "definitions": [
              {
                "definition": "(Zimbabwe) A South African food categorized by strips of lean meat cured by salting and drying, similar to American jerky.",
                "example": null
              }
            ],
            "part_of_speech": "noun",
            "synonyms": []
          }
        ],
        "phonetics": []
      }
    ],
    "photo": "biltong_05122024.jpg",
    "word": "biltong"
  },
  {
    "audio": null,
    "categories": [
      "biology"
    ],
    "level": [
      "C2"
    ],
    "materials": [
      {
        "meanings": [
          {
            "antonyms": [],
            "definitions": [
              {
                "definition": "Any of a group of glycoproteins, produced by the immune system, that prevent viral replication in infected cells.",
                "example": null
              }
            ],
            "part_of_speech": "noun",
            "synonyms": []
          }
        ],
        "phonetics": []
      }
    ],
    "photo": null,
    "word": "interferon"
  },
  {
    "audio": null,
    "categories": [
      "types_of_crime"
    ],
    "level": [
      "C1"
    ],
    "materials": [
      {
        "meanings": [
          {
            "antonyms": [],
            "definitions": [
              {
                "definition": "To seize and detain a person unlawfully; sometimes for ransom.",
                "example": null
              }
            ],
            "part_of_speech": "verb",
            "synonyms": []
          },
          {
            "antonyms": [],
            "definitions": [
              {
                "definition": "The crime of taking a person against their will, sometimes for ransom.",
                "example": null
              }
            ],
            "part_of_speech": "noun",
            "synonyms": []
          }
        ],
        "phonetics": []
      }
    ],
    "photo": "kidnapping_05122024.jpg",
    "word": "kidnapping"
  },
  {
    "audio": null,
    "categories": [
      "parts_of_a_car"
    ],
    "level": [
      "C1"
    ],
    "materials": [
      {
        "meanings": [
          {
            "antonyms": [],
            "definitions": [
              {
                "definition": "A brake in a vehicle that can be set to avoid the vehicle rolling down a hill or being pushed away.",
                "example": null
              }
            ],
            "part_of_speech": "noun",
            "synonyms": [
              "handbrake"
            ]
          }
        ],
        "phonetics": []
      }
    ],
    "photo": "parking brake_05122024.jpg",
    "word": "parking brake"
  },
  {
    "audio": null,
    "categories": [
      "fruit_and_nuts"
    ],
    "level": [
      "C2"
    ],
    "materials": [
      {
        "meanings": [
          {
            "antonyms": [],
            "definitions": [
              {
                "definition": "A shrub belonging to the section Vaccinium sect. Oxycoccus of the genus Vaccinium.",
                "example": null
              },
              {
                "definition": "The edible red berry of that shrub.",
                "example": null
              },
              {
                "definition": "An intense red colour, like that of a cranberry",
                "example": null
              }
            ],
            "part_of_speech": "noun",
            "synonyms": []
          },
          {
            "antonyms": [],
            "definitions": [
              {
                "definition": "Of the intense red colour of a cranberry.",
                "example": null
              }
            ],
            "part_of_speech": "adjective",
            "synonyms": []
          }
        ],
        "phonetics": [
          "/ˈkɹænb(ə)ɹɪ/"
        ]
      }
    ],
    "photo": "cranberry_05122024.jpg",
    "word": "cranberry"
  },
  {
    "audio": null,
    "categories": [
      "likely_to_fail"
    ],
    "level": [
      "C2"
    ],
    "materials": [
      {
        "meanings": [
          {
            "antonyms": [],
            "definitions": [
              {
                "definition": "Doomed to a bad fate; hapless",
                "example": null
              }
            ],
            "part_of_speech": "adjective",
            "synonyms": [
              "star-crossed"
            ]
          }
        ],
        "phonetics": []
      }
    ],
    "photo": "ill-starred_05122024.jpg",
    "word": "ill-starred"
  },
  {
    "audio": null,
    "categories": [
      "relatives"
    ],
    "level": [
      "C1"
    ],
    "materials": [
      {
        "meanings": [
          {
            "antonyms": [],
            "definitions": [
              {
                "definition": "A family consisting of parents and children, along with either grandparents, grandchildren, aunts or uncles, cousins, etc.",
                "example": null
              }
            ],
            "part_of_speech": "noun",
            "synonyms": [
              "whanau"
            ]
          }
        ],
        "phonetics": []
      }
    ],
    "photo": "extended family_05122024.jpg",
    "word": "extended family"
  },
  {
    "audio": null,
    "categories": [
      "wild_mammals"
    ],
    "level": [
      "C2"
    ],
    "materials": [
      {
        "meanings": [
          {
            "antonyms": [],
            "definitions": [
              {
                "definition": "Any of several tropical fruit-eating bats of the family Pteropodidae; a megabat.",
                "example": null
              }
            ],
            "part_of_speech": "noun",
            "synonyms": [
              "flying fox",
              "megabat"
            ]
          }
        ],
        "phonetics": []
      }
    ],
    "photo": "fruit bat_05122024.jpg",
    "word": "fruit bat"
  },
  {
    "audio": [
      "opiate_828_05_12_2024.mp3"
    ],
    "categories": [
      "health_care",
      "drugs"
    ],
    "level": [
      "C2"
    ],
    "materials": [
      {
        "meanings": [
          {
            "antonyms": [],
            "definitions": [
              {
                "definition": "A drug, hormone or other substance derived from or related to opium.",
                "example": null
              },
              {
                "definition": "Something that dulls the senses and induces a false and unrealistic sense of contentment.",
                "example": null
              }
            ],
            "part_of_speech": "noun",
            "synonyms": []
          },
          {
            "antonyms": [],
            "definitions": [
              {
                "definition": "To treat with an opiate drug.",
                "example": null
              }
            ],
            "part_of_speech": "verb",
            "synonyms": []
          },
          {
            "antonyms": [],
            "definitions": [
              {
                "definition": "Relating to, resembling, or containing opium.",
                "example": null
              },
              {
                "definition": "(pharmaceutical effect) Soporific; inducing sleep or sedation.",
                "example": null
              },
              {
                "definition": "Deadening; causing apathy or dullness.",
                "example": null
              }
            ],
            "part_of_speech": "adjective",
            "synonyms": []
          }
        ],
        "phonetics": [
          "/ˈəʊpi.ət/",
          "/ˈoʊpi.ət/",
          "/ˌoʊpieɪt/",
          "/ˈəʊpiˌeɪt/"
        ]
      }
    ],
    "photo": "opiate_05122024.jpg",
    "word": "opiate"
  },
  {
    "audio": null,
    "categories": [
      "recovering_from_illness",
      "operations"
    ],
    "level": [
      "C2"
    ],
    "materials": [
      {
        "meanings": [
          {
            "antonyms": [],
            "definitions": [
              {
                "definition": "Of, relating to, or occurring in the period after a surgical operation.",
                "example": "The postoperative procedure is as follows."
              }
            ],
            "part_of_speech": "adjective",
            "synonyms": []
          }
        ],
        "phonetics": []
      }
    ],
    "photo": "post-operative_05122024.jpg",
    "word": "post-operative"
  },
  {
    "audio": [
      "bulkhead_562_05_12_2024.mp3"
    ],
    "categories": [
      "parts_of_boats",
      "parts_of_a_plane"
    ],
    "level": [
      "C2"
    ],
    "materials": [
      {
        "meanings": [
          {
            "antonyms": [],
            "definitions": [
              {
                "definition": "A vertical partition dividing the hull into separate compartments; often made watertight to prevent excessive flooding if the ship's hull is breached.",
                "example": null
              },
              {
                "definition": "A similar partition in an aircraft or spacecraft.",
                "example": null
              },
              {
                "definition": "Mechanically, a partition or panel through which connectors pass, or a connector designed to pass through a partition.",
                "example": null
              },
              {
                "definition": "A pressure-resistant sealed barrier to any fluid in a large structure.",
                "example": null
              },
              {
                "definition": "A retaining wall along a waterfront.",
                "example": null
              }
            ],
            "part_of_speech": "noun",
            "synonyms": []
          }
        ],
        "phonetics": []
      }
    ],
    "photo": "bulkhead_05122024.jpg",
    "word": "bulkhead"
  },
  {
    "audio": [
      "up-and-coming_469_05_12_2024.mp3"
    ],
    "categories": [
      "achieving_success"
    ],
    "level": [
      "C2"
    ],
    "materials": [
      {
        "meanings": [
          {
            "antonyms": [],
            "definitions": [
              {
                "definition": "Emerging; aspiring; beginning to attract attention or critical acclaim",
                "example": "The theater likes to feature up-and-coming singers and comedians."
              }
            ],
            "part_of_speech": "adjective",
            "synonyms": []
          }
        ],
        "phonetics": []
      }
    ],
    "photo": "up-and-coming_05122024.jpg",
    "word": "up-and-coming"
  },
  {
    "audio": [
      "loudmouth_483_05_12_2024.mp3"
    ],
    "categories": [
      "annoying"
    ],
    "level": [
      "C1"
    ],
    "materials": [
      {
        "meanings": [
          {
            "antonyms": [],
            "definitions": [
              {
                "definition": "One who talks too much or too loudly, especially in a boastful or self-important manner.",
                "example": "I hear every word spoken by the loudmouth in the next office."
              }
            ],
            "part_of_speech": "noun",
            "synonyms": [
              "big mouth",
              "blowhard",
              "blusterer",
              "boaster",
              "braggart"
            ]
          }
        ],
        "phonetics": []
      }
    ],
    "photo": "loudmouth_05122024.jpg",
    "word": "loudmouth"
  },
  {
    "audio": [
      "supple_164_05_12_2024.mp3"
    ],
    "categories": [
      "posture_and_movement"
    ],
    "level": [
      "C2"
    ],
    "materials": [
      {
        "meanings": [
          {
            "antonyms": [],
            "definitions": [
              {
                "definition": "To make or become supple.",
                "example": null
              },
              {
                "definition": "To make compliant, submissive, or obedient.",
                "example": null
              }
            ],
            "part_of_speech": "verb",
            "synonyms": []
          },
          {
            "antonyms": [],
            "definitions": [
              {
                "definition": "Pliant, flexible, easy to bend",
                "example": null
              },
              {
                "definition": "Lithe and agile when moving and bending",
                "example": "supple joints; supple fingers"
              },
              {
                "definition": "Compliant; yielding to the will of others",
                "example": "a supple horse"
              }
            ],
            "part_of_speech": "adjective",
            "synonyms": []
          }
        ],
        "phonetics": [
          "/ˈsʌpəl/"
        ]
      }
    ],
    "photo": "supple_05122024.jpg",
    "word": "supple"
  },
  {
    "audio": [
      "plasma_770_05_12_2024.mp3"
    ],
    "categories": [
      "inside_the_body",
      "molecules_and_matter"
    ],
    "level": [
      "C2"
    ],
    "materials": [
      {
        "meanings": [
          {
            "antonyms": [],
            "definitions": [
              {
                "definition": "A state of matter consisting of partially ionized gas and electrons",
                "example": null
              },
              {
                "definition": "A clear component of blood or lymph containing fibrin",
                "example": null
              },
              {
                "definition": "Blood plasma, free of suspended cells, used in transfusions",
                "example": null
              },
              {
                "definition": "A variety of green quartz, used in ancient times for making engraved ornaments.",
                "example": null
              },
              {
                "definition": "A mixture of starch and glycerin, used as a substitute for ointments.",
                "example": null
              },
              {
                "definition": "A visual effect in which cycles of changing colours are warped in various ways to give the illusion of liquid organic movement.",
                "example": null
              }
            ],
            "part_of_speech": "noun",
            "synonyms": []
          }
        ],
        "phonetics": [
          "/ˈplazmə/"
        ]
      }
    ],
    "photo": "plasma_05122024.jpg",
    "word": "plasma"
  },
  {
    "audio": [
      "chilly_045_05_12_2024.mp3",
      "chilly_559_05_12_2024.mp3"
    ],
    "categories": [
      "temperature"
    ],
    "level": [
      "C1"
    ],
    "materials": [
      {
        "meanings": [
          {
            "antonyms": [],
            "definitions": [
              {
                "definition": "Cold enough to cause discomfort.",
                "example": null
              },
              {
                "definition": "Feeling uncomfortably cold.",
                "example": "I’m getting rather chilly over here – could you shut the window please?"
              },
              {
                "definition": "Distant and cool; unfriendly.",
                "example": "She gave me a chilly look when I made the suggestion."
              }
            ],
            "part_of_speech": "adjective",
            "synonyms": []
          }
        ],
        "phonetics": [
          "/ˈtʃɪli/"
        ]
      },
      {
        "meanings": [
          {
            "antonyms": [],
            "definitions": [
              {
                "definition": "The pungent, spicy fresh or dried fruit of any of several cultivated varieties of capsicum peppers, used in cooking.",
                "example": null
              },
              {
                "definition": "Powdered chili pepper, used as a spice or flavouring in cooking.",
                "example": null
              },
              {
                "definition": "(Indian Chinese cuisine) a spicy stew of chicken or paneer, capsicum and onion, eaten as an appetizer.",
                "example": null
              }
            ],
            "part_of_speech": "noun",
            "synonyms": [
              "chili pepper",
              "chili powder"
            ]
          },
          {
            "antonyms": [],
            "definitions": [
              {
                "definition": "A dish made with chili peppers and other ingredients, such as beans and beef.",
                "example": null
              },
              {
                "definition": "(Cincinnati) Cincinnati chili.",
                "example": null
              }
            ],
            "part_of_speech": "noun",
            "synonyms": [
              "chili con carne"
            ]
          }
        ],
        "phonetics": [
          "/ˈtʃɪli/"
        ]
      }
    ],
    "photo": "chilly_05122024.jpg",
    "word": "chilly"
  },
  {
    "audio": null,
    "categories": [
      "describing_clothes"
    ],
    "level": [
      "C2"
    ],
    "materials": [
      {
        "meanings": [
          {
            "antonyms": [],
            "definitions": [
              {
                "definition": "Very wet; covered in or composed of slop.",
                "example": "The dog tracked sloppy mud through the kitchen!"
              },
              {
                "definition": "Messy; not neat, elegant, or careful.",
                "example": "The carpenter did a sloppy job of building the staircase."
              },
              {
                "definition": "Imprecise or loose.",
                "example": "A sloppy measurement; a sloppy fit!"
              }
            ],
            "part_of_speech": "adjective",
            "synonyms": []
          }
        ],
        "phonetics": []
      }
    ],
    "photo": "sloppy_05122024.jpg",
    "word": "sloppy"
  },
  {
    "audio": null,
    "categories": [
      "producing_music"
    ],
    "level": [
      "C2"
    ],
    "materials": [
      {
        "meanings": [
          {
            "antonyms": [],
            "definitions": [
              {
                "definition": "A type of electronic percussion device.",
                "example": null
              }
            ],
            "part_of_speech": "noun",
            "synonyms": []
          },
          {
            "antonyms": [],
            "definitions": [
              {
                "definition": "To use one’s mouth, lips, tongue, voice, etc. as a percussive instrument to create beats and rhythms for music.",
                "example": null
              }
            ],
            "part_of_speech": "verb",
            "synonyms": []
          }
        ],
        "phonetics": []
      }
    ],
    "photo": "beatbox_05122024.jpg",
    "word": "beatbox"
  },
  {
    "audio": [
      "air marshal_924_05_12_2024.mp3"
    ],
    "categories": [
      "people_in_air_travel",
      "the_air_force"
    ],
    "level": [
      "C2"
    ],
    "materials": [
      {
        "meanings": [
          {
            "antonyms": [],
            "definitions": [
              {
                "definition": "(law enforcement) An armed, undercover guard on a commercial-airline flight.",
                "example": null
              },
              {
                "definition": "A military rank between that of air vice-marshal and air chief marshal, equivalent to an army lieutenant general.",
                "example": null
              }
            ],
            "part_of_speech": "noun",
            "synonyms": [
              "sky marshal"
            ]
          }
        ],
        "phonetics": []
      }
    ],
    "photo": "air marshal_05122024.jpg",
    "word": "air marshal"
  },
  {
    "audio": null,
    "categories": [
      "certainty"
    ],
    "level": [
      "C2"
    ],
    "materials": [
      {
        "meanings": [
          {
            "antonyms": [],
            "definitions": [
              {
                "definition": "(Midwest) A frankfurter, a hot dog.",
                "example": null
              }
            ],
            "part_of_speech": "noun",
            "synonyms": []
          },
          {
            "antonyms": [],
            "definitions": [
              {
                "definition": "Heated to the point that it glows with a visible red color.",
                "example": "The smith's apprentice was still wary of manipulating the red-hot metal."
              },
              {
                "definition": "Very hot",
                "example": "that curry was red-hot"
              },
              {
                "definition": "Emotionally charged, especially with anger or enthusiasm.",
                "example": "He really delivered a red-hot speech today."
              },
              {
                "definition": "Having a very strong sexual appeal.",
                "example": "Did you see that red-hot picture of Liv Tyler in today's paper?"
              },
              {
                "definition": "Very fresh, new, recent and up to date.",
                "example": "Tune in at ten to catch this red-hot story!"
              }
            ],
            "part_of_speech": "adjective",
            "synonyms": []
          }
        ],
        "phonetics": []
      }
    ],
    "photo": "red-hot_05122024.jpg",
    "word": "red-hot"
  },
  {
    "audio": [
      "amber_517_05_12_2024.mp3"
    ],
    "categories": [
      "colours",
      "jewellery"
    ],
    "level": [
      "C2"
    ],
    "materials": [
      {
        "meanings": [
          {
            "antonyms": [
              "green",
              "red"
            ],
            "definitions": [
              {
                "definition": "Ambergris, the waxy product of the sperm whale.",
                "example": null
              },
              {
                "definition": "A hard, generally yellow to brown translucent fossil resin, used for jewellery. One variety, blue amber, appears blue rather than yellow under direct sunlight.",
                "example": null
              },
              {
                "definition": "A yellow-orange colour.",
                "example": null
              },
              {
                "definition": "The intermediate light in a set of three traffic lights, which when illuminated indicates that drivers should stop short of the intersection if it is safe to do so.",
                "example": null
              },
              {
                "definition": "The stop codon (nucleotide triplet) \"UAG\", or a mutant which has this stop codon at a premature place in its DNA sequence.",
                "example": "an amber codon, an amber mutation, an amber suppressor"
              }
            ],
            "part_of_speech": "noun",
            "synonyms": [
              "yellow",
              "ambergris"
            ]
          },
          {
            "antonyms": [],
            "definitions": [
              {
                "definition": "To perfume or flavour with ambergris.",
                "example": "ambered wine, an ambered room"
              },
              {
                "definition": "To preserve in amber.",
                "example": "an ambered fly"
              },
              {
                "definition": "To cause to take on the yellow colour of amber.",
                "example": null
              },
              {
                "definition": "To take on the yellow colour of amber.",
                "example": null
              }
            ],
            "part_of_speech": "verb",
            "synonyms": []
          },
          {
            "antonyms": [],
            "definitions": [
              {
                "definition": "Of a brownish yellow colour, like that of most amber.",
                "example": null
              }
            ],
            "part_of_speech": "adjective",
            "synonyms": []
          }
        ],
        "phonetics": [
          "/ˈam.bə/",
          "/ˈæm.bɚ/"
        ]
      }
    ],
    "photo": "amber_05122024.jpg",
    "word": "amber"
  },
  {
    "audio": null,
    "categories": [
      "carbohydrates"
    ],
    "level": [
      "C2"
    ],
    "materials": [
      {
        "meanings": [
          {
            "antonyms": [],
            "definitions": [
              {
                "definition": "A simple circular, flat, unleavened bread made with sieved wholemeal flour and water, found in Indian cuisine.",
                "example": null
              }
            ],
            "part_of_speech": "noun",
            "synonyms": []
          }
        ],
        "phonetics": []
      }
    ],
    "photo": "chapatti_05122024.jpg",
    "word": "chapatti"
  },
  {
    "audio": null,
    "categories": [
      "types_of_store"
    ],
    "level": [
      "C2"
    ],
    "materials": [
      {
        "meanings": [
          {
            "antonyms": [],
            "definitions": [
              {
                "definition": "One who sells cloths; a dealer in cloths.",
                "example": null
              }
            ],
            "part_of_speech": "noun",
            "synonyms": []
          }
        ],
        "phonetics": [
          "/ˈdɹeɪ.pə(ɹ)/"
        ]
      }
    ],
    "photo": null,
    "word": "draper"
  },
  {
    "audio": [
      "golf course_437_05_12_2024.mp3"
    ],
    "categories": [
      "golf"
    ],
    "level": [
      "B2"
    ],
    "materials": [
      {
        "meanings": [
          {
            "antonyms": [],
            "definitions": [
              {
                "definition": "The land where one plays golf, with tees, fairways, greens and flags in holes.",
                "example": null
              }
            ],
            "part_of_speech": "noun",
            "synonyms": []
          }
        ],
        "phonetics": []
      }
    ],
    "photo": "golf course_05122024.jpg",
    "word": "golf course"
  }
]